Workbook

Sheet Main
A1: repository_owner | B1: repository_name | C1: file_url | D1: sentence_index | E1: sentence_content | F1: Keywords (automatic) | G1: Type of Prohibition
A2: langchain-ai | B2: langchain | C2: https://github.com/langchain-ai/langchain/blob/master/CLAUDE.md | D2: 40 | E2: - Do **not** cite line numbers; they go stale as soon as the file changes. | F2: Do **not** | G2: Commit&PR rule
A3: module-federation | B3: core | C3: https://github.com/module-federation/core/blob/main/CLAUDE.md | D3: 103 | E3: - ✗ Use a single task when multiple would be faster | F3: ✗ | G3: Task Execution
A4: module-federation | B4: core | C4: https://github.com/module-federation/core/blob/main/CLAUDE.md | D4: 104 | E4: - ✗ Ask for clarification before launching tasks | F4: ✗ | G4: Task Execution
A5: module-federation | B5: core | C5: https://github.com/module-federation/core/blob/main/CLAUDE.md | D5: 105 | E5: - ✗ Make tasks dependent on each other | F5: ✗ | G5: Task Execution
A6: module-federation | B6: core | C6: https://github.com/module-federation/core/blob/main/CLAUDE.md | D6: 106 | E6: - ✗ Load entire codebase into a single task | F6: ✗ | G6: Task Execution
A7: module-federation | B7: core | C7: https://github.com/module-federation/core/blob/main/CLAUDE.md | D7: 107 | E7: - ✗ Create documentation unless specifically requested | F7: ✗ | G7: Documentation
A8: module-federation | B8: core | C8: https://github.com/module-federation/core/blob/main/CLAUDE.md | D8: 112 | E8: - ✗ Create new files when existing ones can be modified | F8: ✗ | G8: Task Execution
A9: owid | B9: owid-grapher | C9: https://github.com/owid/owid-grapher/blob/master/CLAUDE.md | D9: 20 | E9: The `makeObservable` call must mention all obserable props, but none of the @computed or @action ones. | F9: none of | G9: Coding Pattern
A10: saleor | B10: saleor | C10: https://github.com/saleor/saleor/blob/main/CLAUDE.md | D10: 20 | E10: - When asserting to Enum, import enum in a test file and use `assert error.code == MyEnum.SOME_ERROR.name` instead of plain string comparison | F10: instead of | G10: Coding Pattern
A11: zed-industries | B11: zed | C11: https://github.com/zed-industries/zed/blob/main/CLAUDE.md | D11: 111 | E11: Do **not** edit `.rules` inline during normal feature/fix work. | F11: Do **not** | G11: Documentation
A12: gluesql | B12: glues | C12: https://github.com/gluesql/glues/blob/main/AGENTS.md | D12: 4 | E12: - Use file-based module declarations; do **not** introduce `mod.rs` files. | F12: Do **not** | G12: Coding Pattern
A13: useautumn | B13: autumn | C13: https://github.com/useautumn/autumn/blob/main/AGENTS.md | D13: 30 | E13: - Do **not** remove or bypass logic in `server/src/honoMiddlewares/refreshCacheMiddleware.ts` unless the user explicitly asks to change middleware behavior globally. | F13: Do **not** | G13: Coding Pattern
A14: Azure | B14: fleet | C14: https://github.com/Azure/fleet/blob/main/.github/copilot-instructions.md | D14: 32 | E14: - Do **not** use assert libraries; use `cmp.Diff` / `cmp.Equal` from `google/go-cmp` for comparisons | F14: Do **not** | G14: Coding Pattern
A15: dotnet | B15: java-interop | C15: https://github.com/dotnet/java-interop/blob/main/.github/copilot-instructions.md | D15: 46 | E15: * Use `""` for empty string and *not* `string.Empty` | G15: Coding Pattern
A16: dotnet | B16: java-interop | C16: https://github.com/dotnet/java-interop/blob/main/.github/copilot-instructions.md | D16: 47 | E16: * Use `[]` for empty arrays and *not* `Array.Empty<T>()` | G16: Coding Pattern
A17: dotnet | B17: maui | C17: https://github.com/dotnet/maui/blob/main/.github/copilot-instructions.md | D17: 106 | E17: Direct commits to `main` are strictly prohibited. | F17: prohibited | G17: Commit&PR rule
A18: kubefleet-dev | B18: kubefleet | C18: https://github.com/kubefleet-dev/kubefleet/blob/main/.github/copilot-instructions.md | D18: 32 | E18: - Do **not** use assert libraries; use `cmp.Diff` / `cmp.Equal` from `google/go-cmp` for comparisons | F18: Do **not** | G18: Coding Pattern
A19: wled | B19: WLED | C19: https://github.com/wled/WLED/blob/main/.github/copilot-instructions.md | D19: 7 | E19: Do **not** use that content as actionable review | F19: Do **not** | G19: Code Review
A20: abh | B20: ntppool | C20: https://github.com/abh/ntppool/blob/main/CLAUDE.md | D20: 121 | E20: ❌ **Shadow DOM by default**: Use `inherit-styles="true"` for Web Components | F20: ❌ | G20: Coding Pattern
A21: home-assistant | B21: frontend | C21: https://github.com/home-assistant/frontend/blob/master/CLAUDE.md | D21: 225 | E21: - ❌ "Create New Automation" | F21: ❌ | G21: Writing Style Preference
A22: home-assistant | B22: frontend | C22: https://github.com/home-assistant/frontend/blob/master/CLAUDE.md | D22: 227 | E22: - ❌ "Device Settings" | F22: ❌ | G22: Writing Style Preference
A23: paradigmxyz | B23: reth | C23: https://github.com/paradigmxyz/reth/blob/main/CLAUDE.md | D23: 138 | E23: ❌ **Bad**: Adding new traits and auxiliary types **above** the file's primary type (see [#22133](https://github.com/paradigmxyz/reth/pull/22133)): | F23: ❌ | G23: Coding Style
A24: julep-ai | B24: julep | C24: https://github.com/julep-ai/julep/blob/main/AGENTS.md | D24: 21 | E24: | ❌ Touch `tests/`, `SPEC.md`, or any `*_spec.py` / `*.ward` files (humans own tests & specs). | F24: ❌ | G24: Testing
A25: julep-ai | B25: julep | C25: https://github.com/julep-ai/julep/blob/main/AGENTS.md | D25: 24 | E25: | ❌ Delete or mangle existing `AIDEV-` comments. | F25: ❌ | G25: Documentation
A26: julep-ai | B26: julep | C26: https://github.com/julep-ai/julep/blob/main/AGENTS.md | D26: 28 | E26: | ❌ Re-format code to any other style. | F26: ❌ | G26: Coding Style
A27: julep-ai | B27: julep | C27: https://github.com/julep-ai/julep/blob/main/AGENTS.md | D27: 35 | E27: | ❌ Continue work from a prior prompt after "new task" – start a fresh session. | F27: ❌ | G27: Task Execution
A28: public-ui | B28: kolibri | C28: https://github.com/public-ui/kolibri/blob/master/AGENTS.md | D28: 81 | E28: ❌ **Outdated pattern (removed):** | F28: ❌ | G28: Coding Pattern
... A2505: CapSoftware | B2505: Cap | C2505: https://github.com/CapSoftware/Cap/blob/main/AGENTS.md | D2505: 85 | E2505: - On the client, use `useEffectQuery`/`useEffectMutation` from `@/lib/EffectRuntime`; they already bind the managed runtime and tracing so you shouldn't call `EffectRuntime.run*` directly in components. | F2505: shouldn't | G2505: Coding Pattern
A2506: colinhacks | B2506: zod | C2506: https://github.com/colinhacks/zod/blob/main/CLAUDE.md | D2506: 69 | E2506: - Skip effusive praise: "Great work", "Awesome", "Thanks so much for this", "Thanks for the careful writeup", "you clearly read the RFC". | G2506: Writing Style Preference
A2507: colinhacks | B2507: zod | C2507: https://github.com/colinhacks/zod/blob/main/CLAUDE.md | D2507: 99 | E2507: - Skip emojis in substantive technical writeups. | G2507: Commit&PR rule
A2508: module-federation | B2508: core | C2508: https://github.com/module-federation/core/blob/main/CLAUDE.md | D2508: 111 | E2508: - ✗ Skip running tests after changes | F2508: ✗ | G2508: Testing
A2509: microsoft | B2509: typespec | C2509: https://github.com/microsoft/typespec/blob/main/.github/copilot-instructions.md | D2509: 75 | E2509: - For new features, include a short code block in the changelog entry that showcases the new functionality; skip code blocks for simple bug fixes. | G2509: Commit&PR rule
A2510: microsoft | B2510: vs-threading | C2510: https://github.com/microsoft/vs-threading/blob/main/.github/copilot-instructions.md | D2510: 15 | E2510: When running tests, you should skip the unstable ones by using `-- --filter-not-trait "FailsInCloudTest=true"`. | F2510: should **not** | G2510: Testing
A2511: sybrew | B2511: the-seo-framework | C2511: https://github.com/sybrew/the-seo-framework/blob/master/.github/copilot-instructions.md | D2511: 47 | E2511: Skip ritual closings. | G2511: Writing Style Preference
A2512: coder | B2512: coder | C2512: https://github.com/coder/coder/blob/main/CLAUDE.md | D2512: 3 | E2512: Rule #1: If you want exception to ANY rule, YOU MUST STOP and get explicit permission first. | F2512: STOP | G2512: Task Execution
A2513: Pipelex | B2513: pipelex | C2513: https://github.com/Pipelex/pipelex/blob/main/CLAUDE.md | D2513: 127 | E2513: If you find yourself writing `except Exception`, STOP and ask the user before proceeding. | F2513: STOP | G2513: Task Execution
A2514: RchGrav | B2514: claudebox | C2514: https://github.com/RchGrav/claudebox/blob/main/CLAUDE.md | D2514: 103 | E2514: * `-euo pipefail` stops on non-zero status, undefined vars, or broken pipelines. | F2514: STOP | G2514: Build & Operation
A2515: Skyvern-AI | B2515: skyvern | C2515: https://github.com/Skyvern-AI/skyvern/blob/master/CLAUDE.md | D2515: 7 | E2515: - **Stop services**: `skyvern stop all` | F2515: STOP | G2515: Build & Operation
A2516: steipete | B2516: Peekaboo | C2516: https://github.com/steipete/Peekaboo/blob/main/CLAUDE.md | D2516: 16 | E2516: - Rapid rebuilds while editing Swift: `pnpm run poltergeist:haunt` → check with `pnpm run poltergeist:status`, stop via `pnpm run poltergeist:rest`. | F2516: STOP | G2516: Build & Operation
A2517: xlnfinance | B2517: xln | C2517: https://github.com/xlnfinance/xln/blob/main/CLAUDE.md | D2517: 9 | E2517: **ABSOLUTE RULE - violation = stop and report immediately:** | F2517: STOP | G2517: Task Execution
A2518: xlnfinance | B2518: xln | C2518: https://github.com/xlnfinance/xln/blob/main/CLAUDE.md | D2518: 16 | E2518: - Stop coding | F2518: STOP | G2518: Task Execution
A2519: xlnfinance | B2519: xln | C2519: https://github.com/xlnfinance/xln/blob/main/CLAUDE.md | D2519: 42 | E2519: - **<80%**: Stop and ask (multiple valid paths, UX unclear, architectural choice) | F2519: STOP | G2519: Task Execution
A2520: Pipelex | B2520: pipelex | C2520: https://github.com/Pipelex/pipelex/blob/main/AGENTS.md | D2520: 106 | E2520: If you find yourself writing `except Exception`, STOP and ask the user before proceeding. | F2520: STOP | G2520: Task Execution
A2521: james-gould | B2521: azure-keyvault-emulator | C2521: https://github.com/james-gould/azure-keyvault-emulator/blob/master/.github/copilot-instructions.md | D2521: 59 | E2521: Stop existing processes using this port. | F2521: STOP | G2521: Build & Operation
A2522: sybrew | B2522: the-seo-framework | C2522: https://github.com/sybrew/the-seo-framework/blob/master/.github/copilot-instructions.md | D2522: 115 | E2522: - If you believe a file is corrupted, stop immediately and wait for a new instruction. | F2522: STOP | G2522: Task Execution
A2523: xlnfinance | B2523: xln | C2523: https://github.com/xlnfinance/xln/blob/main/CLAUDE.md | D2523: 21 | E2523: **Remembered from 2025-12-29 session:** Spent 2+ hours on hacks (fake registration, event patches, ownReserve='0' conditionals) instead of stopping and asking. | F2523: instead of, STOP | G2523: Task Execution
... A2543: dailydotdev | B2543: apps | C2543: https://github.com/dailydotdev/apps/blob/main/CLAUDE.md | D2543: 120 | E2543: - ❌ **Wrong**: Local `stripHtml()` in webapp-only file | F2543: ❌ | G2543: Coding Pattern

Sheet Results
A1: Label | B1: Category Name | C1: Description | D1: Rule | E1: Example | F1: # | G1: %
A2: Commit&PR rule | B2: Version Control Interaction | C2: Prohibitions on commit behavior, pull request content, branch interaction, and changelog formatting. These instructions govern how the agent interacts with the version control system and collaborative development artifacts. | D2: The instruction refers to commit messages, PR messages, interaction with the repository, commit behavior, etc | E2: Direct commits to `main` are strictly prohibited. | F2: =COUNTIF(Main!G:G,A2) -> 198 | G2: =(F2/J14) -> 0.077891424 | H2: RULES
A3: Task Execution | B3: Workflow and Artifacts Management | C3: Prohibitions on how the agent should manage and execute tasks: workflow sequencing, context loading, task decomposition, parallelism, and general operational behavior during execution. These instructions govern agent autonomy at the process level. | D3: The instruction refers to how the agent should execute tasks, workflow, how it should handle instructions, how to be efficient when executing tasks, and generally how it should act | E3: - **MINIMIZE CONTEXT**: Avoid loading unnecessary files to preserve token efficiency | F3: =COUNTIF(Main!G:G,A3) -> 428 | G3: =(F3/J14) -> 0.16837136 | H3: - During coding, when you are unsure of a category, please come back to this codebook to verify detection rule - You can improve detection rules as you go over new data to be more informative of what they can be assigned to - You can add other categories, if they emerge from the data and they are shared among multiple instructions - If you add a new category, that must be discussed when the step completes, so remember it - If all agree with the new category, add it in this codebook specifying detection rule and an example so that it can be used for next step by all coders
A4: Documentation | B4: Documentation | C4: Prohibitions on the creation, modification, or formatting of documentation artifacts, including Markdown files, inline code comments, and project guidelines. These instructions often constrain unsolicited documentation generation or unauthorized edits to existing artifacts. | D4: The instruction relates to any kind of documentation artifact (.md, code comments, guidelines) and how the agent should interact with them | E4: - ✗ Create documentation unless specifically requested | F4: =COUNTIF(Main!G:G,A4) -> 159 | G4: =(F4/J14) -> 0.062549174
A5: Coding Pattern | B5: Coding Pattern | C5: Prohibitions on how the agent should functionally implement code, including imports, type annotations, design patterns, control flow constructs, and use of specific APIs or libraries. These instructions constrain implementation choices at the logic level. | D5: The instruction refers to how the agent should functionally write code (typings, imports, design patterns, loops, conditions) | E5: - Avoid inline for loops, unless it's ultra-simple and holds on oneline. | F5: =COUNTIF(Main!G:G,A5) -> 755 | G5: =(F5/J14) -> 0.29701023
A6: Code Review | B6: Code Review and Inspection | C6: Prohibitions on how the agent should conduct or participate in code review, including scope of feedback, use of review content as directives, and interaction with artifacts under review. | D6: The instruction mentions how the agent should handle code review, artifact review, and interact with the code written by others | E6: Do **not** use that content as actionable review | F6: =COUNTIF(Main!G:G,A6) -> 21 | G6: =(F6/J14) -> 0.0082612116
A7: Writing Style Preference | B7: Writing and Communication Style | C7: Prohibitions on the agent's use of natural language, covering tone, terminology, abbreviations, formatting conventions, and clarity. These instructions apply to any text the agent produces outside of source code. | D7: The instruction mentions how the agent should write natural language, patterns, clarity, and quality | E7: - **Avoid CAPS for emphasis**: Use bold or italics instead | F7: =COUNTIF(Main!G:G,A7) -> 88 | G7: =(F7/J14) -> 0.034618411
A8: Coding Style | B8: Coding Style | C8: Prohibitions on the stylistic presentation of code, including naming conventions, formatting, file organization, and comment structure. These instructions address how code should look rather than what it should do. | D8: The instruction mentions how the agent should adapt the code style in terms of preferences of how the code should look (not functionality), like names etc. | E8: - Avoid redundant function header comments that merely repeat the function name. | F8: =COUNTIF(Main!G:G,A8) -> 171 | G8: =(F8/J14) -> 0.067269866
A9: Testing | B9: Test Development and Execution | C9: Prohibitions related to test code, test files, testing strategies, and verification artifacts. These instructions restrict what the agent may modify or create in the testing layer, including ownership boundaries between human- and agent-managed test artifacts. | D9: The instruction relates to tests, testing, verification, test files, test code | E9: - **Test simplicity**: Keep tests simple, avoid mocks. | F9: =COUNTIF(Main!G:G,A9) -> 255 | G9: =(F9/J14) -> 0.10031471
A10: Maintainability | B10: Maintainability and Quality | C10: Prohibitions targeting code quality attributes beyond immediate functionality, such as unnecessary complexity, code duplication, over-engineering, and architectural fragility. These instructions reflect long-term maintainability concerns. | D10: The instruction mentions quality attributes of the code that improve maintainability like complexity, readability, etc | E10: **Avoid architectural complexity** - simple functions over design patterns | F10: =COUNTIF(Main!G:G,A10) -> 44 | G10: =(F10/J14) -> 0.017309205
A11: Build & Operation | B11: Build, Operation and Environment | C11: Prohibitions on build processes, compilation, environment setup, and operational tooling such as servers, containers, and CI/CD pipelines. These instructions constrain agent actions that interact with the execution environment rather than the source code itself. | D11: The instruction refers about operational before or after the developement e.g Building, Compiling, etc. Development Environment is also considered as a part of Build & Operation | E11: - Avoid running Docker or external services yourself unless requested; root workflows handle them as needed. | F11: =COUNTIF(Main!G:G,A11) -> 249 | G11: =(F11/J14) -> 0.097954367
A12: Performance | B12: Performance and Efficiency | C12: Prohibitions on implementation choices that could degrade runtime performance or resource efficiency, including unnecessary allocations, inefficient data structures, excessive dependencies, and anti-patterns in hot paths. | D12: The instruction refers to how to create code that is performant, fast, efficient, etc | E12: - Avoid introducing new external dependencies unless it will have a material impact on code readability or performance | F12: =COUNTIF(Main!G:G,A12) -> 49 | G12: =(F12/J14) -> 0.019276161
A13: Security | B13: Security and Privacy | C13: Prohibitions related to security risks, credential handling, secret management, sensitive data exposure, and cybersecurity best practices. These instructions encode hard boundaries against actions that could compromise system or data integrity. | D13: The instruction mentions security threats, secrets, personal informations, or cybersec | E13: - Secrets managed via Azure (Function App / Static Web App settings) – Avoid committing secrets | F13: =COUNTIF(Main!G:G,A13) -> 80 | G13: =(F13/J14) -> 0.031471282
A14: Other | F14: =COUNTIF(Main!G:G,A14) -> 0 | G14: =(F14/J14) -> 0 | I14: TOTAL: | J14: =COUNTA(Main!E2:E2846) -> 2542
A15: NOT_ENOUGH_CONTEXT | D15: It does not have enough contexts | E15: Avoid: | F15: =COUNTIF(Main!G:G,A15) -> 45 | G15: =(F15/J14) -> 0.017702596
F17: =SUM(F1:F15) -> 2542 | G17: =SUM(G2:G15) -> 1

Sheet Step 1
A1: ACF | B1: Instruction | C1: Category | D1: Reason
A2: https://github.com/langchain-ai/langchain/blob/master/CLAUDE.md | B2: - Do **not** cite line numbers; they go stale as soon as the file changes. | C2: Commit&PR rule | D2: cite number is not nessesary
A3: https://github.com/module-federation/core/blob/main/CLAUDE.md | B3: - ✗ Use a single task when multiple would be faster | C3: Task Execution | D3: working with a single task is slower
A4: https://github.com/module-federation/core/blob/main/CLAUDE.md | B4: - ✗ Ask for clarification before launching tasks | C4: Task Execution | D4: Ask for clarification
A5: https://github.com/module-federation/core/blob/main/CLAUDE.md | B5: - ✗ Make tasks dependent on each other | C5: Task Execution | D5: dependency-lock to each other tasks
A6: https://github.com/module-federation/core/blob/main/CLAUDE.md | B6: - ✗ Load entire codebase into a single task | C6: Task Execution | D6: dont load all codebase in a single task
A7: https://github.com/module-federation/core/blob/main/CLAUDE.md | B7: - ✗ Create documentation unless specifically requested | C7: Documentation | D7: dont create documents unrequested, don't do something i did not request
A8: https://github.com/module-federation/core/blob/main/CLAUDE.md | B8: - ✗ Create new files when existing ones can be modified | C8: Task Execution | D8: dont create new things thate we already have
A9: https://github.com/owid/owid-grapher/blob/master/CLAUDE.md | B9: The `makeObservable` call must mention all obserable props, but none of the @computed or @action ones. | C9: Coding Pattern | D9: don't use a particular type of props in the code
A10: https://github.com/saleor/saleor/blob/main/CLAUDE.md | B10: - When asserting to Enum, import enum in a test file and use `assert error.code == MyEnum.SOME_ERROR.name` instead of plain string comparison | C10: Coding Pattern | D10: do not use plain string comparison
A11: https://github.com/zed-industries/zed/blob/main/CLAUDE.md | B11: Do **not** edit `.rules` inline during normal feature/fix work. | C11: Documentation
A12: https://github.com/gluesql/glues/blob/main/AGENTS.md | B12: - Use file-based module declarations; do **not** introduce `mod.rs` files. | C12: Coding Pattern | D12: prohibit the pattern of introduing mod.rs
A13: https://github.com/useautumn/autumn/blob/main/AGENTS.md | B13: - Do **not** remove or bypass logic in `server/src/honoMiddlewares/refreshCacheMiddleware.ts` unless the user explicitly asks to change middleware behavior globally. | C13: Coding Pattern
A14: https://github.com/Azure/fleet/blob/main/.github/copilot-instructions.md | B14: - Do **not** use assert libraries; use `cmp.Diff` / `cmp.Equal` from `google/go-cmp` for comparisons | C14: Coding Pattern
A15: https://github.com/dotnet/java-interop/blob/main/.github/copilot-instructions.md | B15: * Use `""` for empty string and *not* `string.Empty` | C15: Coding Pattern | D15: clearly state about the pattern of the code for empty string
A16: https://github.com/dotnet/java-interop/blob/main/.github/copilot-instructions.md | B16: * Use `[]` for empty arrays and *not* `Array.Empty<T>()` | C16: Coding Pattern | D16: clearly state about the pattern of the code for empty array
A17: https://github.com/dotnet/maui/blob/main/.github/copilot-instructions.md | B17: Direct commits to `main` are strictly prohibited. | C17: Commit&PR rule | D17: its prohibit commiting to main branch
A18: https://github.com/kubefleet-dev/kubefleet/blob/main/.github/copilot-instructions.md | B18: - Do **not** use assert libraries; use `cmp.Diff` / `cmp.Equal` from `google/go-cmp` for comparisons | C18: Coding Pattern | D18: Clarify what can and cannot be done.
A19: https://github.com/wled/WLED/blob/main/.github/copilot-instructions.md | B19: Do **not** use that content as actionable review | C19: Code Review
A20: https://github.com/abh/ntppool/blob/main/CLAUDE.md | B20: ❌ **Shadow DOM by default**: Use `inherit-styles="true"` for Web Components | C20: Coding Pattern
A21: https://github.com/home-assistant/frontend/blob/master/CLAUDE.md | B21: - ❌ "Create New Automation" | C21: Writing Style Preference
A22: https://github.com/home-assistant/frontend/blob/master/CLAUDE.md | B22: - ❌ "Device Settings" | C22: Writing Style Preference
A23: https://github.com/paradigmxyz/reth/blob/main/CLAUDE.md | B23: ❌ **Bad**: Adding new traits and auxiliary types **above** the file's primary type (see [#22133](https://github.com/paradigmxyz/reth/pull/22133)): | C23: Coding Style
A24: https://github.com/julep-ai/julep/blob/main/AGENTS.md | B24: | ❌ Touch `tests/`, `SPEC.md`, or any `*_spec.py` / `*.ward` files (humans own tests & specs). | C24: Testing
A25: https://github.com/julep-ai/julep/blob/main/AGENTS.md | B25: | ❌ Delete or mangle existing `AIDEV-` comments. | C25: Documentation | D25: keep the comment in the code
A26: https://github.com/julep-ai/julep/blob/main/AGENTS.md | B26: | ❌ Re-format code to any other style. | C26: Coding Style | D26: keep code-format consistent
A27: https://github.com/julep-ai/julep/blob/main/AGENTS.md | B27: | ❌ Continue work from a prior prompt after "new task" – start a fresh session. | C27: Task Execution
A28: https://github.com/public-ui/kolibri/blob/master/AGENTS.md | B28: ❌ **Outdated pattern (removed):** | C28: Coding Pattern | D28: outdate pattern
A29: https://github.com/dotnet/docs-desktop/blob/main/.github/copilot-instructions.md | B29: - ❌ Bad: `Getting-Started-With-The-Entity-Framework.md` | C29: Documentation | D29: in the context, they said how to name the file
A30: https://github.com/dotnet/docs-desktop/blob/main/.github/copilot-instructions.md | B30: - ❌ Bad: `configure_logging.md` | C30: Documentation | D30: in the context, they said how to name the file
A31: https://github.com/dotnet/docs-desktop/blob/main/.github/copilot-instructions.md | B31: - ❌ Bad: `DependencyInjectionGuidelines.md` | C31: Documentation | D31: in the context, they said how to name the file
A32: https://github.com/raycast/extensions/blob/main/.github/copilot-instructions.md | B32: - ❌ Incorrect: `## [Bug Fix] - 2024-07-12` | C32: Commit&PR rule
A33: https://github.com/geneontology/go-ontology/blob/master/CLAUDE.md | B33: Similarly, it's generally an anti-pattern to have more than one asserted `is_a`. | C33: Coding Pattern | D33: code anti-pattern mentioned
A34: https://github.com/geneontology/go-ontology/blob/master/CLAUDE.md | B34: A common anti-pattern is using logical definitions where relationships suffice. | C34: Coding Pattern | D34: code anti-pattern mentioned
A35: https://github.com/dotnet/maui/blob/main/.github/copilot-instructions.md | B35: **Anti-pattern:** Writing ad-hoc scripts to parse AzDO build timelines. | C35: Coding Pattern | D35: code anti-pattern mentioned
A36: https://github.com/geneontology/go-ontology/blob/master/.github/copilot-instructions.md | B36: Similarly, it's generally an anti-pattern to have more than one asserted `is_a`. | C36: Coding Pattern | D36: code anti-pattern mentioned
A37: https://github.com/geneontology/go-ontology/blob/master/.github/copilot-instructions.md | B37: A common anti-pattern is using logical definitions where relationships suffice. | C37: Coding Pattern | D37: code anti-pattern mentioned
A38: https://github.com/abh/ntppool/blob/main/CLAUDE.md | B38: - Keep functions focused and avoid over-engineering with design patterns | C38: Maintainability | D38: over-enginnering mentioned.
A39: https://github.com/abh/ntppool/blob/main/CLAUDE.md | B39: **Avoid architectural complexity** - simple functions over design patterns | C39: Maintainability | D39: clearly state about using simpler function more than follow design pattern
A40: https://github.com/abh/ntppool/blob/main/CLAUDE.md | B40: - **`account_id`**: AVOID - use `a` parameter with account token instead | C40: Coding Style | D40: naming rule
A41: https://github.com/ajanraj/OpenChat/blob/main/CLAUDE.md | B41: Avoid `any` and `unknown` types. | C41: Coding Pattern
A42: https://github.com/ajanraj/OpenChat/blob/main/CLAUDE.md | B42: Avoid inline styles. | C42: Coding Pattern
A43: https://github.com/badlogic/lemmy/blob/main/CLAUDE.md | B43: **CRITICAL: Avoid `any` at all costs!** Use proper TypeScript types wherever possible: | C43: Coding Pattern
A44: https://github.com/BerriAI/litellm/blob/main/CLAUDE.md | B44: - **Avoid imports within methods** — place all imports at the top of the file (module-level). | C44: Coding Pattern | D44: import all of dependencies in the top of file
A45: https://github.com/CapSoftware/Cap/blob/main/CLAUDE.md | B45: - Avoid `any`. | C45: Coding Pattern
A46: https://github.com/CapSoftware/Cap/blob/main/CLAUDE.md | B46: Avoid starting multiple overlapping servers. | C46: Build & Operation
A47: https://github.com/CapSoftware/Cap/blob/main/CLAUDE.md | B47: - Avoid running Docker or external services yourself unless requested; root workflows handle them as needed. | C47: Build & Operation
A48: https://github.com/CapSoftware/Cap/blob/main/CLAUDE.md | B48: The middleware/utility already hydrate `CurrentUser`, so avoid duplicating session lookups in route handlers. | C48: Coding Pattern | D48: Exisiting of `CurrentUser` has been assured by the architecture
A49: https://github.com/CapSoftware/Cap/blob/main/CLAUDE.md | B49: - Windowing/permissions are handled in Rust; keep UI logic in Solid and avoid mixing IPC with rendering logic. | C49: Coding Pattern | D49: Porhibiting messy usage of IPC(Inter Process Communication)
A50: https://github.com/cloudposse/atmos/blob/main/CLAUDE.md | B50: - Avoid integration tests by mocking external dependencies | C50: Testing
A51: https://github.com/cloudposse/atmos/blob/main/CLAUDE.md | B51: - Avoid tautological tests | C51: Testing
A52: https://github.com/cloudwalk/stratus/blob/main/CLAUDE.md | B52: - `wildcard_imports = "warn"` - Avoid `use module::*` | C52: Coding Pattern
A53: https://github.com/cockroachdb/cockroach/blob/master/CLAUDE.md | B53: Avoid doing this unless necessary. | C53: Build & Operation | D53: Original sentence: ```Building a CockroachDB binary (even in short mode) should be considered slow. Avoid doing this unless necessary.```
A54: https://github.com/coder/coder/blob/main/CLAUDE.md | B54: - Avoid `ByX` names for grouped queries. | C54: Coding Style
A55: https://github.com/compiler-explorer/compiler-explorer/blob/main/CLAUDE.md | B55: - Avoid redundant function header comments that merely repeat the function name. | C55: Coding Style
A56: https://github.com/compiler-explorer/infra/blob/main/CLAUDE.md | B56: - Avoid emojis | C56: Commit&PR rule
A57: https://github.com/compiler-explorer/infra/blob/main/CLAUDE.md | B57: - Avoid "LLM tells", for example: | C57: Commit&PR rule
A58: https://github.com/compiler-explorer/infra/blob/main/CLAUDE.md | B58: - Avoid cliches | C58: Commit&PR rule
A59: https://github.com/dailydotdev/apps/blob/main/CLAUDE.md | B59: Avoid large content images that dominate the layout unless image content is the primary purpose. | C59: Code Review
A60: https://github.com/dailydotdev/apps/blob/main/CLAUDE.md | B60: - **Keep scope tight in design iterations** - When adjusting UI, avoid unrelated behavioral/SEO changes in the same commit unless explicitly requested. | C60: Code Review
A61: https://github.com/FastLED/FastLED/blob/master/CLAUDE.md | B61: - **Test simplicity**: Keep tests simple, avoid mocks. | C61: Testing | D61: keep tests simple
A62: https://github.com/FastLED/FastLED/blob/master/CLAUDE.md | B62: Avoid introducing bugs. | C62: Maintainability
A63: https://github.com/Freika/dawarich/blob/master/CLAUDE.md | B63: }, prefix: :field_name` to get scoped predicate methods and avoid name collisions. | C63: Coding Style
A64: https://github.com/fukuball/jieba-php/blob/master/CLAUDE.md | B64: - Avoid dynamic tag generation from untrusted sources | C64: Coding Pattern
A65: https://github.com/gensx-inc/gensx/blob/main/CLAUDE.md | B65: - Always use explicit imports, avoid default imports where possible | C65: Coding Pattern
A66: https://github.com/getsentry/sentry-cocoa/blob/main/CLAUDE.md | B66: Avoid `-C` when you can change directory instead | C66: Task Execution
A67: https://github.com/getsentry/sentry-javascript/blob/master/CLAUDE.md | B67: Prefer LSP over Grep/Read for code navigation — it's faster, precise, and avoids reading entire files: | C67: Task Execution
A68: https://github.com/grafbase/grafbase/blob/main/CLAUDE.md | B68: For new components, avoid creating many small files. | C68: Task Execution
A69: https://github.com/grafbase/grafbase/blob/main/CLAUDE.md | B69: Avoid test names like `test_` and prefer using terms like "can", "should", "must" or "given" to define a property/behavior the code should uphold. | C69: Testing | D69: test naming strategy
A70: https://github.com/home-assistant/frontend/blob/master/CLAUDE.md | B70: - **Always use strict TypeScript**: Enable all strict flags, avoid `any` types | C70: Coding Pattern
A71: https://github.com/home-assistant/frontend/blob/master/CLAUDE.md | B71: - **Avoid jargon**: Use terms familiar to home automation users | C71: Writing Style Preference | D71: use simple terms
A72: https://github.com/home-assistant/frontend/blob/master/CLAUDE.md | B72: - **Avoid abbreviations**: Spell out terms when possible | C72: Writing Style Preference | D72: avoid abbreviations
A73: https://github.com/home-assistant/frontend/blob/master/CLAUDE.md | B73: - **Avoid CAPS for emphasis**: Use bold or italics instead | C73: Writing Style Preference | D73: use bold or italics
A74: https://github.com/home-assistant/frontend/blob/master/CLAUDE.md | B74: - [ ] Avoids abbreviations and jargon | C74: Writing Style Preference | D74: avoid abbreviations and jargon
A75: CLAUDE.md - J-Tech-Japan/Sekiban · GitHub | B75: - Keep actor (grain) boundaries explicit; avoid embedding cross-cutting logic directly inside web/API layers. | C75: Coding Pattern
A76: https://github.com/JuliaBesties/BestieTemplate.jl/blob/main/CLAUDE.md | B76: The Julia session stays alive between calls, avoiding recompilation. | C76: Build & Operation
A77: https://github.com/JuliaBesties/BestieTemplate.jl/blob/main/CLAUDE.md | B77: Note: It might out of date, so it is better to avoid until reviewed. | C77: Writing Style Preference
A78: https://github.com/jxnl/blog/blob/main/CLAUDE.md | B78: **Subheadings:** Avoid corny/dramatic language. | C78: Writing Style Preference | D78: This is a github page repo ?
A79: https://github.com/jxnl/blog/blob/main/CLAUDE.md | B79: - Avoid overly dramatic or "thought leadership" subheadings | C79: Writing Style Preference
A80: https://github.com/kubetail-org/kubetail/blob/main/CLAUDE.md | B80: - Avoid introducing new external dependencies unless it will have a material impact on code readability or performance | C80: Performance
A81: https://github.com/langchain-ai/langchain/blob/master/CLAUDE.md | B81: Avoid insider shorthand and prefer language that is friendly to public viewers — this aids interpretability. | C81: Commit&PR rule | D81: Write for readers who may be unfamiliar with this area of the codebase. Avoid insider shorthand and prefer language that is friendly to public viewers — this aids interpretability.
A82: https://github.com/lfnovo/esperanto/blob/main/CLAUDE.md | B82: - Avoids loading all providers at import time | C82: Build & Operation | D82: load only used dependency, dynamically is not meaning loading all of providers
A83: https://github.com/module-federation/core/blob/main/CLAUDE.md | B83: **Maximum 10 tasks**: Avoid over-fragmentation; combine related work | C83: Task Execution | D83: maximum 10 tasks
A84: https://github.com/module-federation/core/blob/main/CLAUDE.md | B84: - **MINIMIZE CONTEXT**: Avoid loading unnecessary files to preserve token efficiency | C84: Task Execution
A85: https://github.com/module-federation/core/blob/main/CLAUDE.md | B85: - Avoid redundant file reads across tasks | C85: Task Execution | D85: context management across tasks
A86: https://github.com/nrwl/nx/blob/master/CLAUDE.md | B86: - Prefix nx commands with the workspace's package manager (e.g., `pnpm nx build`, `npm exec nx test`) - avoids using globally installed CLI | C86: Build & Operation
A87: https://github.com/open-metadata/OpenMetadata/blob/main/CLAUDE.md | B87: - **State Management**: Use `useState` with proper typing, avoid `any` | C87: Coding Pattern | D87: please clearly state the type
A88: https://github.com/open-metadata/OpenMetadata/blob/main/CLAUDE.md | B88: - Custom styles in `.less` files with component-specific naming (legacy pattern, avoid for new code) | C88: Coding Style
A89: https://github.com/open-metadata/OpenMetadata/blob/main/CLAUDE.md | B89: - Avoid type assertions unless absolutely necessary | C89: Coding Pattern
A90: CLAUDE.md - owid/etl · GitHub | B90: - **Garden: `safe_types=False`** — for large tables (>1M rows), use `ds.read("table", safe_types=False)` to preserve categoricals and avoid expensive type conversions. | C90: Performance | D90: This sentence is included in "Performance" section in original ACF
A91: https://github.com/owid/owid-grapher/blob/master/CLAUDE.md | B91: - Avoid the use of the `any` type. | C91: Coding Pattern | D91: please clearly state the type
A92: https://github.com/paradigmxyz/reth/blob/main/CLAUDE.md | B92: **Avoid Allocations in Hot Paths**: Use references and borrowing | C92: Performance | D92: following just references and borrowing stradegy not Hot Path
A93: https://github.com/paradigmxyz/reth/blob/main/CLAUDE.md | B93: Based on PR patterns, avoid: | C93: Commit&PR rule
A94: https://github.com/pdfme/pdfme/blob/main/CLAUDE.md | B94: - **Type Safety**: Ensure proper type definitions and avoid `any` types | C94: Coding Pattern
A95: https://github.com/Pipelex/pipelex/blob/main/CLAUDE.md | B95: Avoid unless using the `exceptiongroup` backport. | C95: Build & Operation
A96: https://github.com/Pipelex/pipelex/blob/main/CLAUDE.md | B96: - Avoid inline for loops, unless it's ultra-simple and holds on oneline. | C96: Coding Pattern
A97: https://github.com/Pipelex/pipelex/blob/main/CLAUDE.md | B97: - Avoid as much as possible import statements outside of a module's top-level scope. | C97: Coding Pattern
A98: https://github.com/Pipelex/pipelex/blob/main/CLAUDE.md | B98: - Note how we avoid initializing a default mutable value within a class instance, instead we use ClassVar. | C98: Coding Pattern
A99: https://github.com/RchGrav/claudebox/blob/main/CLAUDE.md | B99: * Avoid `stat` entirely—output formats diverge. | C99: Coding Pattern
A100: https://github.com/RchGrav/claudebox/blob/main/CLAUDE.md | B100: Code snippets should be avoided. | C100: Documentation
...

Sheet Ann1 - Step 2
A1: Column 3 | B1: Instruction | C1: Category
A2: https://github.com/saleor/saleor/blob/main/CLAUDE.md | B2: - Avoid assertion to plain values, if you already have references to existing value. | C2: Testing | F2: Testing
A3: https://github.com/saleor/saleor/blob/main/CLAUDE.md | B3: 1000 rows) to avoid long-running transactions | C3: Task Execution | F3: Task Execution
A4: https://github.com/spylang/spy/blob/main/CLAUDE.md | B4: Avoid writing useless comments: if you need to write a comment, explain WHY the code | C4: Documentation | F4: Documentation
A5: https://github.com/steipete/Peekaboo/blob/main/CLAUDE.md | B5: - SwiftLint config lives in `.swiftlint.yml`; keep new code typed (avoid `Any`), prefer small scoped extensions over large files. | C5: Coding Style | F5: Coding Style
A6: https://github.com/steipete/Peekaboo/blob/main/CLAUDE.md | B6: - Use `./scripts/committer "type(scope): summary" <paths…>` to stage and create commits; avoid raw `git add`. | C6: Commit&PR rule | F6: Commit&PR rule
A7: https://github.com/steipete/Peekaboo/blob/main/CLAUDE.md | B7: - Respect permissions flows documented in `docs/permissions.md`; avoid editing derived artifacts—regenerate via the provided scripts instead. | C7: Build & Operation | F7: Build & Operation
A8: https://github.com/stepfunc/dnp3/blob/main/CLAUDE.md | B8: - **API Design**: Avoid unreachable public items (`unreachable_pub = "deny"`) | C8: Coding Style | F8: Maintainability
A9: https://github.com/thirdweb-dev/js/blob/main/CLAUDE.md | B9: Avoid personal names | C9: Commit&PR rule | F9: Coding Pattern
A10: https://github.com/thirdweb-dev/js/blob/main/CLAUDE.md | B10: - Avoid editor-specific configs; rely on shared settings | C10: Coding Style | F10: Writing Style Preference
A11: https://github.com/thirdweb-dev/js/blob/main/CLAUDE.md | B11: - **Type safety**: Avoid `any` and `unknown` unless unavoidable; narrow generics when possible | C11: Coding Style | F11: Security
A12: https://github.com/thirdweb-dev/js/blob/main/CLAUDE.md | B12: - **Test approach**: Use real function invocations with stub data; avoid brittle mocks | C12: Testing | F12: Performance
A13: https://github.com/thirdweb-dev/js/blob/main/CLAUDE.md | B13: - Return typed results (`Project[]`, `User[]`) – avoid `any` | C13: Coding Style | F13: Code Review
A14: https://github.com/tphakala/birdnet-go/blob/main/CLAUDE.md | B14: Check open PRs to avoid conflicts | C14: Commit&PR rule
A15: https://github.com/truenas/webui/blob/master/CLAUDE.md | B15: - Avoid the `any` type; use `unknown` when type is uncertain | C15: Coding Style
A16: https://github.com/truenas/webui/blob/master/CLAUDE.md | B16: **Avoid** (constructor injection): | C16: Coding Style
A17: https://github.com/wolfi-dev/os/blob/main/CLAUDE.md | B17: - Avoid using obsolete package versions | C17: Maintainability
A18: https://github.com/wolfi-dev/os/blob/main/CLAUDE.md | B18: - When adding tests, always review existing tests and avoid creating redundant tests. | C18: Testing
A19: https://github.com/wvlet/airframe/blob/main/CLAUDE.md | B19: - Avoid `Try[A]` return types - use plain exceptions or domain-specific errors | C19: Coding Style
A20: https://github.com/wvlet/airframe/blob/main/CLAUDE.md | B20: - Avoid mocks to reduce maintenance cost | C20: Maintainability
A21: https://github.com/wvlet/wvlet/blob/main/CLAUDE.md | B21: - Avoid using mock as it increases maintenance cost and creates brittle tests that break when internal implementation changes | C21: Maintainability
A22: https://github.com/wvlet/wvlet/blob/main/CLAUDE.md | B22: - Avoid: `"testParseJSON"`, `"test1"`, `"shouldWork"` | C22: Testing
A23: https://github.com/wvlet/wvlet/blob/main/CLAUDE.md | B23: - Avoid returning Try[A] as it forces monadic-style usage | C23: Coding Style
A24: https://github.com/wvlet/wvlet/blob/main/CLAUDE.md | B24: - **In Scala.js code, avoid using Java-specific libraries** | C24: Coding Pattern
A25: https://github.com/wvlet/wvlet/blob/main/CLAUDE.md | B25: - Avoid: `feature: Add XXX class` | C25: Coding Pattern
... A501: https://github.com/marin-community/marin/blob/main/AGENTS.md | B501: - do not use storage transfer service to move files from one region to another unless the user says "I personally will write grants for Percy to pay for this" | C501: Task Execution

Sheet Ann2 - Step 2
A1: Column 3 | B1: Instruction | C1: Category
A2: https://github.com/saleor/saleor/blob/main/CLAUDE.md | B2: - Avoid assertion to plain values, if you already have references to existing value. | C2: Testing | F2: Testing
A3: https://github.com/saleor/saleor/blob/main/CLAUDE.md | B3: 1000 rows) to avoid long-running transactions | C3: Coding Pattern | F3: Coding Pattern
A4: https://github.com/spylang/spy/blob/main/CLAUDE.md | B4: Avoid writing useless comments: if you need to write a comment, explain WHY the code | C4: Documentation | F4: Documentation
A5: https://github.com/steipete/Peekaboo/blob/main/CLAUDE.md | B5: - SwiftLint config lives in `.swiftlint.yml`; keep new code typed (avoid `Any`), prefer small scoped extensions over large files. | C5: Coding Pattern | F5: Commit&PR rule
A6: https://github.com/steipete/Peekaboo/blob/main/CLAUDE.md | B6: - Use `./scripts/committer "type(scope): summary" <paths…>` to stage and create commits; avoid raw `git add`. | C6: Commit&PR rule | F6: Coding Style
A7: https://github.com/steipete/Peekaboo/blob/main/CLAUDE.md | B7: - Respect permissions flows documented in `docs/permissions.md`; avoid editing derived artifacts—regenerate via the provided scripts instead. | C7: Documentation | F7: Task Execution
A8: https://github.com/stepfunc/dnp3/blob/main/CLAUDE.md | B8: - **API Design**: Avoid unreachable public items (`unreachable_pub = "deny"`) | C8: Coding Pattern | F8: Writing Style Preference
A9: https://github.com/thirdweb-dev/js/blob/main/CLAUDE.md | B9: Avoid personal names | C9: Commit&PR rule | F9: Security
A10: https://github.com/thirdweb-dev/js/blob/main/CLAUDE.md | B10: - Avoid editor-specific configs; rely on shared settings | C10: Coding Style | F10: Build & Operation
A11: https://github.com/thirdweb-dev/js/blob/main/CLAUDE.md | B11: - **Type safety**: Avoid `any` and `unknown` unless unavoidable; narrow generics when possible | C11: Coding Pattern | F11: Maintainability
A12: https://github.com/thirdweb-dev/js/blob/main/CLAUDE.md | B12: - **Test approach**: Use real function invocations with stub data; avoid brittle mocks | C12: Testing | F12: Performance
A13: https://github.com/thirdweb-dev/js/blob/main/CLAUDE.md | B13: - Return typed results (`Project[]`, `User[]`) – avoid `any` | C13: Coding Pattern | F13: Code Review
A14: https://github.com/tphakala/birdnet-go/blob/main/CLAUDE.md | B14: Check open PRs to avoid conflicts | C14: Commit&PR rule | F14: Other
A15: https://github.com/truenas/webui/blob/master/CLAUDE.md | B15: - Avoid the `any` type; use `unknown` when type is uncertain | C15: Coding Pattern
A16: https://github.com/truenas/webui/blob/master/CLAUDE.md | B16: **Avoid** (constructor injection): | C16: Coding Pattern
A17: https://github.com/wolfi-dev/os/blob/main/CLAUDE.md | B17: - Avoid using obsolete package versions | C17: Coding Pattern
A18: https://github.com/wolfi-dev/os/blob/main/CLAUDE.md | B18: - When adding tests, always review existing tests and avoid creating redundant tests. | C18: Testing
A19: https://github.com/wvlet/airframe/blob/main/CLAUDE.md | B19: - Avoid `Try[A]` return types - use plain exceptions or domain-specific errors | C19: Coding Pattern
A20: https://github.com/wvlet/airframe/blob/main/CLAUDE.md | B20: - Avoid mocks to reduce maintenance cost | C20: Testing
A21: https://github.com/wvlet/wvlet/blob/main/CLAUDE.md | B21: - Avoid using mock as it increases maintenance cost and creates brittle tests that break when internal implementation changes | C21: Testing
A22: https://github.com/wvlet/wvlet/blob/main/CLAUDE.md | B22: - Avoid: `"testParseJSON"`, `"test1"`, `"shouldWork"` | C22: Coding Style
A23: https://github.com/wvlet/wvlet/blob/main/CLAUDE.md | B23: - Avoid returning Try[A] as it forces monadic-style usage | C23: Coding Pattern
A24: https://github.com/wvlet/wvlet/blob/main/CLAUDE.md | B24: - **In Scala.js code, avoid using Java-specific libraries** | C24: Coding Pattern
A25: https://github.com/wvlet/wvlet/blob/main/CLAUDE.md | B25: - Avoid: `feature: Add XXX class` | C25: Commit&PR rule
A26: https://github.com/yamadashy/repomix/blob/main/CLAUDE.md | B26: - Maintain feature-based directory structure and avoid dependencies between features | C26: Coding Pattern
... A501: https://github.com/marin-community/marin/blob/main/AGENTS.md | B501: - do not use storage transfer service to move files from one region to another unless the user says "I personally will write grants for Percy to pay for this" | C501: Task Execution

Sheet Step2 Merge
A1: URL | B1: Instruction | C1: Ann1 | D1: Ann2
A2: ='Ann1 - Step 2'!A2 -> https://github.com/saleor/saleor/blob/main/CLAUDE.md | B2: ='Ann1 - Step 2'!B2 -> - Avoid assertion to plain values, if you already have references to existing value. | C2: ='Ann1 - Step 2'!C2 -> Testing | D2: ='Ann2 - Step 2'!C2 -> Testing | E2: =IF(C2=D2, FALSE, TRUE) -> FALSE | G2: =IF(E2=TRUE,F2,D2) -> Testing
A3: ='Ann1 - Step 2'!A3 -> https://github.com/saleor/saleor/blob/main/CLAUDE.md | B3: ='Ann1 - Step 2'!B3 -> 1000 rows) to avoid long-running transactions | C3: ='Ann1 - Step 2'!C3 -> Task Execution | D3: ='Ann2 - Step 2'!C3 -> Coding Pattern | E3: =IF(C3=D3, FALSE, TRUE) -> TRUE | F3: Task Execution | G3: =IF(E3=TRUE,F3,D3) -> Task Execution
A4: ='Ann1 - Step 2'!A4 -> https://github.com/spylang/spy/blob/main/CLAUDE.md | B4: ='Ann1 - Step 2'!B4 -> Avoid writing useless comments: if you need to write a comment, explain WHY the code | C4: ='Ann1 - Step 2'!C4 -> Documentation | D4: ='Ann2 - Step 2'!C4 -> Documentation | E4: =IF(C4=D4, FALSE, TRUE) -> FALSE | G4: =IF(E4=TRUE,F4,D4) -> Documentation
A5: ='Ann1 - Step 2'!A5 -> https://github.com/steipete/Peekaboo/blob/main/CLAUDE.md | B5: ='Ann1 - Step 2'!B5 -> - SwiftLint config lives in `.swiftlint.yml`; keep new code typed (avoid `Any`), prefer small scoped extensions over large files. | C5: ='Ann1 - Step 2'!C5 -> Coding Style | D5: ='Ann2 - Step 2'!C5 -> Coding Pattern | E5: =IF(C5=D5, FALSE, TRUE) -> TRUE | F5: Coding Pattern | G5: =IF(E5=TRUE,F5,D5) -> Coding Pattern
A6: ='Ann1 - Step 2'!A6 -> https://github.com/steipete/Peekaboo/blob/main/CLAUDE.md | B6: ='Ann1 - Step 2'!B6 -> - Use `./scripts/committer "type(scope): summary" <paths…>` to stage and create commits; avoid raw `git add`. | C6: ='Ann1 - Step 2'!C6 -> Commit&PR rule | D6: ='Ann2 - Step 2'!C6 -> Commit&PR rule | E6: =IF(C6=D6, FALSE, TRUE) -> FALSE | G6: =IF(E6=TRUE,F6,D6) -> Commit&PR rule
A7: ='Ann1 - Step 2'!A7 -> https://github.com/steipete/Peekaboo/blob/main/CLAUDE.md | B7: ='Ann1 - Step 2'!B7 -> - Respect permissions flows documented in `docs/permissions.md`; avoid editing derived artifacts—regenerate via the provided scripts instead. | C7: ='Ann1 - Step 2'!C7 -> Build & Operation | D7: ='Ann2 - Step 2'!C7 -> Documentation | E7: =IF(C7=D7, FALSE, TRUE) -> TRUE | F7: Build & Operation | G7: =IF(E7=TRUE,F7,D7) -> Build & Operation
A8: ='Ann1 - Step 2'!A8 -> https://github.com/stepfunc/dnp3/blob/main/CLAUDE.md | B8: ='Ann1 - Step 2'!B8 -> - **API Design**: Avoid unreachable public items (`unreachable_pub = "deny"`) | C8: ='Ann1 - Step 2'!C8 -> Coding Style | D8: ='Ann2 - Step 2'!C8 -> Coding Pattern | E8: =IF(C8=D8, FALSE, TRUE) -> TRUE | F8: Coding Pattern | G8: =IF(E8=TRUE,F8,D8) -> Coding Pattern
A9: ='Ann1 - Step 2'!A9 -> https://github.com/thirdweb-dev/js/blob/main/CLAUDE.md | B9: ='Ann1 - Step 2'!B9 -> Avoid personal names | C9: ='Ann1 - Step 2'!C9 -> Commit&PR rule | D9: ='Ann2 - Step 2'!C9 -> Commit&PR rule | E9: =IF(C9=D9, FALSE, TRUE) -> FALSE | G9: =IF(E9=TRUE,F9,D9) -> Commit&PR rule
A10: ='Ann1 - Step 2'!A10 -> https://github.com/thirdweb-dev/js/blob/main/CLAUDE.md | B10: ='Ann1 - Step 2'!B10 -> - Avoid editor-specific configs; rely on shared settings | C10: ='Ann1 - Step 2'!C10 -> Coding Style | D10: ='Ann2 - Step 2'!C10 -> Coding Style | E10: =IF(C10=D10, FALSE, TRUE) -> FALSE | G10: =IF(E10=TRUE,F10,D10) -> Coding Style
A11: ='Ann1 - Step 2'!A11 -> https://github.com/thirdweb-dev/js/blob/main/CLAUDE.md | B11: ='Ann1 - Step 2'!B11 -> - **Type safety**: Avoid `any` and `unknown` unless unavoidable; narrow generics when possible | C11: ='Ann1 - Step 2'!C11 -> Coding Style | D11: ='Ann2 - Step 2'!C11 -> Coding Pattern | E11: =IF(C11=D11, FALSE, TRUE) -> TRUE | F11: Coding Pattern | G11: =IF(E11=TRUE,F11,D11) -> Coding Pattern
A12: ='Ann1 - Step 2'!A12 -> https://github.com/thirdweb-dev/js/blob/main/CLAUDE.md | B12: ='Ann1 - Step 2'!B12 -> - **Test approach**: Use real function invocations with stub data; avoid brittle mocks | C12: ='Ann1 - Step 2'!C12 -> Testing | D12: ='Ann2 - Step 2'!C12 -> Testing | E12: =IF(C12=D12, FALSE, TRUE) -> FALSE | G12: =IF(E12=TRUE,F12,D12) -> Testing
A13: ='Ann1 - Step 2'!A13 -> https://github.com/thirdweb-dev/js/blob/main/CLAUDE.md | B13: ='Ann1 - Step 2'!B13 -> - Return typed results (`Project[]`, `User[]`) – avoid `any` | C13: ='Ann1 - Step 2'!C13 -> Coding Style | D13: ='Ann2 - Step 2'!C13 -> Coding Pattern | E13: =IF(C13=D13, FALSE, TRUE) -> TRUE | F13: Coding Pattern | G13: =IF(E13=TRUE,F13,D13) -> Coding Pattern
A14: ='Ann1 - Step 2'!A14 -> https://github.com/tphakala/birdnet-go/blob/main/CLAUDE.md | B14: ='Ann1 - Step 2'!B14 -> Check open PRs to avoid conflicts | C14: ='Ann1 - Step 2'!C14 -> Commit&PR rule | D14: ='Ann2 - Step 2'!C14 -> Commit&PR rule | E14: =IF(C14=D14, FALSE, TRUE) -> FALSE | G14: =IF(E14=TRUE,F14,D14) -> Commit&PR rule
A15: ='Ann1 - Step 2'!A15 -> https://github.com/truenas/webui/blob/master/CLAUDE.md | B15: ='Ann1 - Step 2'!B15 -> - Avoid the `any` type; use `unknown` when type is uncertain | C15: ='Ann1 - Step 2'!C15 -> Coding Style | D15: ='Ann2 - Step 2'!C15 -> Coding Pattern | E15: =IF(C15=D15, FALSE, TRUE) -> TRUE | F15: Coding Pattern | G15: =IF(E15=TRUE,F15,D15) -> Coding Pattern
A16: ='Ann1 - Step 2'!A16 -> https://github.com/truenas/webui/blob/master/CLAUDE.md | B16: ='Ann1 - Step 2'!B16 -> **Avoid** (constructor injection): | C16: ='Ann1 - Step 2'!C16 -> Coding Style | D16: ='Ann2 - Step 2'!C16 -> Coding Pattern | E16: =IF(C16=D16, FALSE, TRUE) -> TRUE | F16: Coding Pattern | G16: =IF(E16=TRUE,F16,D16) -> Coding Pattern
A17: ='Ann1 - Step 2'!A17 -> https://github.com/wolfi-dev/os/blob/main/CLAUDE.md | B17: ='Ann1 - Step 2'!B17 -> - Avoid using obsolete package versions | C17: ='Ann1 - Step 2'!C17 -> Maintainability | D17: ='Ann2 - Step 2'!C17 -> Coding Pattern | E17: =IF(C17=D17, FALSE, TRUE) -> TRUE | F17: Build & Operation | G17: =IF(E17=TRUE,F17,D17) -> Build & Operation
A18: ='Ann1 - Step 2'!A18 -> https://github.com/wolfi-dev/os/blob/main/CLAUDE.md | B18: ='Ann1 - Step 2'!B18 -> - When adding tests, always review existing tests and avoid creating redundant tests. | C18: ='Ann1 - Step 2'!C18 -> Testing | D18: ='Ann2 - Step 2'!C18 -> Testing | E18: =IF(C18=D18, FALSE, TRUE) -> FALSE | G18: =IF(E18=TRUE,F18,D18) -> Testing
A19: ='Ann1 - Step 2'!A19 -> https://github.com/wvlet/airframe/blob/main/CLAUDE.md | B19: ='Ann1 - Step 2'!B19 -> - Avoid `Try[A]` return types - use plain exceptions or domain-specific errors | C19: ='Ann1 - Step 2'!C19 -> Coding Style | D19: ='Ann2 - Step 2'!C19 -> Coding Pattern | E19: =IF(C19=D19, FALSE, TRUE) -> TRUE | F19: Coding Pattern | G19: =IF(E19=TRUE,F19,D19) -> Coding Pattern
A20: ='Ann1 - Step 2'!A20 -> https://github.com/wvlet/airframe/blob/main/CLAUDE.md | B20: ='Ann1 - Step 2'!B20 -> - Avoid mocks to reduce maintenance cost | C20: ='Ann1 - Step 2'!C20 -> Maintainability | D20: ='Ann2 - Step 2'!C20 -> Testing | E20: =IF(C20=D20, FALSE, TRUE) -> TRUE | F20: Testing | G20: =IF(E20=TRUE,F20,D20) -> Testing
A21: ='Ann1 - Step 2'!A21 -> https://github.com/wvlet/wvlet/blob/main/CLAUDE.md | B21: ='Ann1 - Step 2'!B21 -> - Avoid using mock as it increases maintenance cost and creates brittle tests that break when internal implementation changes | C21: ='Ann1 - Step 2'!C21 -> Maintainability | D21: ='Ann2 - Step 2'!C21 -> Testing | E21: =IF(C21=D21, FALSE, TRUE) -> TRUE | F21: Testing | G21: =IF(E21=TRUE,F21,D21) -> Testing
A22: ='Ann1 - Step 2'!A22 -> https://github.com/wvlet/wvlet/blob/main/CLAUDE.md | B22: ='Ann1 - Step 2'!B22 -> - Avoid: `"testParseJSON"`, `"test1"`, `"shouldWork"` | C22: ='Ann1 - Step 2'!C22 -> Testing | D22: ='Ann2 - Step 2'!C22 -> Coding Style | E22: =IF(C22=D22, FALSE, TRUE) -> TRUE | F22: Testing | G22: =IF(E22=TRUE,F22,D22) -> Testing
A23: ='Ann1 - Step 2'!A23 -> https://github.com/wvlet/wvlet/blob/main/CLAUDE.md | B23: ='Ann1 - Step 2'!B23 -> - Avoid returning Try[A] as it forces monadic-style usage | C23: ='Ann1 - Step 2'!C23 -> Coding Style | D23: ='Ann2 - Step 2'!C23 -> Coding Pattern | E23: =IF(C23=D23, FALSE, TRUE) -> TRUE | F23: Coding Pattern | G23: =IF(E23=TRUE,F23,D23) -> Coding Pattern
A24: ='Ann1 - Step 2'!A24 -> https://github.com/wvlet/wvlet/blob/main/CLAUDE.md | B24: ='Ann1 - Step 2'!B24 -> - **In Scala.js code, avoid using Java-specific libraries** | C24: ='Ann1 - Step 2'!C24 -> Coding Pattern | D24: ='Ann2 - Step 2'!C24 -> Coding Pattern | E24: =IF(C24=D24, FALSE, TRUE) -> FALSE | G24: =IF(E24=TRUE,F24,D24) -> Coding Pattern
A25: ='Ann1 - Step 2'!A25 -> https://github.com/wvlet/wvlet/blob/main/CLAUDE.md | B25: ='Ann1 - Step 2'!B25 -> - Avoid: `feature: Add XXX class` | C25: ='Ann1 - Step 2'!C25 -> Coding Pattern | D25: ='Ann2 - Step 2'!C25 -> Commit&PR rule | E25: =IF(C25=D25, FALSE, TRUE) -> TRUE | F25: Commit&PR rule | G25: =IF(E25=TRUE,F25,D25) -> Commit&PR rule
A26: ='Ann1 - Step 2'!A26 -> https://github.com/yamadashy/repomix/blob/main/CLAUDE.md | B26: ='Ann1 - Step 2'!B26 -> - Maintain feature-based directory structure and avoid dependencies between features | C26: ='Ann1 - Step 2'!C26 -> Coding Pattern | D26: ='Ann2 - Step 2'!C26 -> Coding Pattern | E26: =IF(C26=D26, FALSE, TRUE) -> FALSE | G26: =IF(E26=TRUE,F26,D26) -> Coding Pattern
A27: ='Ann1 - Step 2'!A27 -> https://github.com/zed-industries/zed/blob/main/CLAUDE.md | B27: ='Ann1 - Step 2'!B27 -> Avoid creating many small files. | C27: ='Ann1 - Step 2'!C27 -> Coding Pattern | D27: ='Ann2 - Step 2'!C27 -> Task Execution | E27: =IF(C27=D27, FALSE, TRUE) -> TRUE | F27: Task Execution | G27: =IF(E27=TRUE,F27,D27) -> Task Execution
A28: ='Ann1 - Step 2'!A28 -> https://github.com/zed-industries/zed/blob/main/CLAUDE.md | B28: ='Ann1 - Step 2'!B28 -> * Avoid using functions that panic like `unwrap()`, instead use mechanisms like `?` to propagate errors. | C28: ='Ann1 - Step 2'!C28 -> Coding Pattern | D28: ='Ann2 - Step 2'!C28 -> Coding Pattern | E28: =IF(C28=D28, FALSE, TRUE) -> FALSE | G28: =IF(E28=TRUE,F28,D28) -> Coding Pattern
A29: ='Ann1 - Step 2'!A29 -> https://github.com/zed-industries/zed/blob/main/CLAUDE.md | B29: ='Ann1 - Step 2'!B29 -> - Example: avoid `let _ = client.request(...).await?;` - use `client.request(...).await?;` instead | C29: ='Ann1 - Step 2'!C29 -> Coding Pattern | D29: ='Ann2 - Step 2'!C29 -> Coding Style | E29: =IF(C29=D29, FALSE, TRUE) -> TRUE | F29: Coding Style | G29: =IF(E29=TRUE,F29,D29) -> Coding Style
A30: ='Ann1 - Step 2'!A30 -> https://github.com/zed-industries/zed/blob/main/CLAUDE.md | B30: ='Ann1 - Step 2'!B30 -> * Avoid creative additions unless explicitly requested | C30: ='Ann1 - Step 2'!C30 -> Coding Pattern | D30: ='Ann2 - Step 2'!C30 -> Task Execution | E30: =IF(C30=D30, FALSE, TRUE) -> TRUE | F30: Task Execution | G30: =IF(E30=TRUE,F30,D30) -> Task Execution
A31: ='Ann1 - Step 2'!A31 -> https://github.com/zed-industries/zed/blob/main/CLAUDE.md | B31: ='Ann1 - Step 2'!B31 -> Trying to update an entity while it's already being updated must be avoided as this will cause a panic. | C31: ='Ann1 - Step 2'!C31 -> Build & Operation | D31: ='Ann2 - Step 2'!C31 -> Task Execution | E31: =IF(C31=D31, FALSE, TRUE) -> TRUE | F31: Coding Pattern | G31: =IF(E31=TRUE,F31,D31) -> Coding Pattern
A32: ='Ann1 - Step 2'!A32 -> https://github.com/zed-industries/zed/blob/main/CLAUDE.md | B32: ='Ann1 - Step 2'!B32 -> `SharedString` is used to avoid copying strings, and is either an `&'static str` or `Arc<str>`. | C32: ='Ann1 - Step 2'!C32 -> Build & Operation | D32: ='Ann2 - Step 2'!C32 -> Coding Pattern | E32: =IF(C32=D32, FALSE, TRUE) -> TRUE | F32: Coding Pattern | G32: =IF(E32=TRUE,F32,D32) -> Coding Pattern
A33: ='Ann1 - Step 2'!A33 -> https://github.com/zed-industries/zed/blob/main/CLAUDE.md | B33: ='Ann1 - Step 2'!B33 -> - Avoid conventional commit prefixes in PR titles (`fix:`, `feat:`, `docs:`, etc.). | C33: ='Ann1 - Step 2'!C33 -> Commit&PR rule | D33: ='Ann2 - Step 2'!C33 -> Commit&PR rule | E33: =IF(C33=D33, FALSE, TRUE) -> FALSE | G33: =IF(E33=TRUE,F33,D33) -> Commit&PR rule
A34: ='Ann1 - Step 2'!A34 -> https://github.com/zed-industries/zed/blob/main/CLAUDE.md | B34: ='Ann1 - Step 2'!B34 -> - Avoid trailing punctuation in PR titles. | C34: ='Ann1 - Step 2'!C34 -> Commit&PR rule | D34: ='Ann2 - Step 2'!C34 -> Commit&PR rule | E34: =IF(C34=D34, FALSE, TRUE) -> FALSE | G34: =IF(E34=TRUE,F34,D34) -> Commit&PR rule
A35: ='Ann1 - Step 2'!A35 -> https://github.com/zed-industries/zed/blob/main/CLAUDE.md | B35: ='Ann1 - Step 2'!B35 -> Avoid architectural descriptions of a crate (module layout, data flow, key types). | C35: ='Ann1 - Step 2'!C35 -> Documentation | D35: ='Ann2 - Step 2'!C35 -> Task Execution | E35: =IF(C35=D35, FALSE, TRUE) -> TRUE | F35: Documentation | G35: =IF(E35=TRUE,F35,D35) -> Documentation
A36: ='Ann1 - Step 2'!A36 -> https://github.com/zenml-io/zenml/blob/main/CLAUDE.md | B36: ='Ann1 - Step 2'!B36 -> - Avoid simple explanatory comments, where it is already clear from the code itself. | C36: ='Ann1 - Step 2'!C36 -> Documentation | D36: ='Ann2 - Step 2'!C36 -> Documentation | E36: =IF(C36=D36, FALSE, TRUE) -> FALSE | G36: =IF(E36=TRUE,F36,D36) -> Documentation
A37: ='Ann1 - Step 2'!A37 -> https://github.com/zenml-io/zenml/blob/main/CLAUDE.md | B37: ='Ann1 - Step 2'!B37 -> - Avoid useless one-line comments interleaved with code that merely narrate the implementation. | C37: ='Ann1 - Step 2'!C37 -> Documentation | D37: ='Ann2 - Step 2'!C37 -> Documentation | E37: =IF(C37=D37, FALSE, TRUE) -> FALSE | G37: =IF(E37=TRUE,F37,D37) -> Documentation
A38: ='Ann1 - Step 2'!A38 -> https://github.com/zenml-io/zenml/blob/main/CLAUDE.md | B38: ='Ann1 - Step 2'!B38 -> > ⚠️ **Integrations should avoid using ZenML private methods** | C38: ='Ann1 - Step 2'!C38 -> Build & Operation | D38: ='Ann2 - Step 2'!C38 -> Coding Pattern | E38: =IF(C38=D38, FALSE, TRUE) -> TRUE | F38: Coding Pattern | G38: =IF(E38=TRUE,F38,D38) -> Coding Pattern
A39: ='Ann1 - Step 2'!A39 -> https://github.com/zenml-io/zenml/blob/main/CLAUDE.md | B39: ='Ann1 - Step 2'!B39 -> - Avoid vague language ("thing", "stuff", "value", "setting") | C39: ='Ann1 - Step 2'!C39 -> Writing Style Preference | D39: ='Ann2 - Step 2'!C39 -> Writing Style Preference | E39: =IF(C39=D39, FALSE, TRUE) -> FALSE | G39: =IF(E39=TRUE,F39,D39) -> Writing Style Preference
A40: ='Ann1 - Step 2'!A40 -> https://github.com/zenml-io/zenml/blob/main/CLAUDE.md | B40: ='Ann1 - Step 2'!B40 -> - Avoid overusing bullet points or other formatting elements | C40: ='Ann1 - Step 2'!C40 -> Writing Style Preference | D40: ='Ann2 - Step 2'!C40 -> Writing Style Preference | E40: =IF(C40=D40, FALSE, TRUE) -> FALSE | G40: =IF(E40=TRUE,F40,D40) -> Writing Style Preference
A41: ='Ann1 - Step 2'!A41 -> https://github.com/ArcInstitute/SRAgent/blob/main/AGENTS.md | B41: ='Ann1 - Step 2'!B41 -> - Add tests for new features and edge cases; avoid network‑dependent tests unless mocked. | C41: ='Ann1 - Step 2'!C41 -> Testing | D41: ='Ann2 - Step 2'!C41 -> Testing | E41: =IF(C41=D41, FALSE, TRUE) -> FALSE | G41: =IF(E41=TRUE,F41,D41) -> Testing
A42: ='Ann1 - Step 2'!A42 -> https://github.com/Azure-Samples/serverless-chat-langchainjs/blob/main/AGENTS.md | B42: ='Ann1 - Step 2'!B42 -> - Maintain simplicity; avoid premature abstractions or heavy frameworks | C42: ='Ann1 - Step 2'!C42 -> Coding Pattern | D42: ='Ann2 - Step 2'!C42 -> Coding Pattern | E42: =IF(C42=D42, FALSE, TRUE) -> FALSE | G42: =IF(E42=TRUE,F42,D42) -> Coding Pattern
A43: ='Ann1 - Step 2'!A43 -> https://github.com/Azure-Samples/serverless-chat-langchainjs/blob/main/AGENTS.md | B43: ='Ann1 - Step 2'!B43 -> - Secrets managed via Azure (Function App / Static Web App settings) – Avoid committing secrets | C43: ='Ann1 - Step 2'!C43 -> Security | D43: ='Ann2 - Step 2'!C43 -> Security | E43: =IF(C43=D43, FALSE, TRUE) -> FALSE | G43: =IF(E43=TRUE,F43,D43) -> Security
A44: ='Ann1 - Step 2'!A44 -> https://github.com/bruin-data/bruin/blob/main/AGENTS.md | B44: ='Ann1 - Step 2'!B44 -> **Avoid lock-in**: Open-source Apache-licensed, runs anywhere | C44: ='Ann1 - Step 2'!C44 -> Coding Pattern | D44: ='Ann2 - Step 2'!C44 -> Build & Operation | E44: =IF(C44=D44, FALSE, TRUE) -> TRUE | F44: Build & Operation | G44: =IF(E44=TRUE,F44,D44) -> Build & Operation
A45: ='Ann1 - Step 2'!A45 -> https://github.com/CapSoftware/Cap/blob/main/AGENTS.md | B45: ='Ann1 - Step 2'!B45 -> - Avoid `any`. | C45: ='Ann1 - Step 2'!C45 -> Coding Pattern | D45: ='Ann2 - Step 2'!C45 -> Coding Pattern | E45: =IF(C45=D45, FALSE, TRUE) -> FALSE | G45: =IF(E45=TRUE,F45,D45) -> Coding Pattern
A46: ='Ann1 - Step 2'!A46 -> https://github.com/CapSoftware/Cap/blob/main/AGENTS.md | B46: ='Ann1 - Step 2'!B46 -> - Convert the effectful API to a Next.js handler with `apiToHandler(ApiLive)` from `@/lib/server` and export the returned `handler`—avoid calling `runPromise` inside route files. | C46: ='Ann1 - Step 2'!C46 -> Build & Operation | D46: ='Ann2 - Step 2'!C46 -> Coding Pattern | E46: =IF(C46=D46, FALSE, TRUE) -> TRUE | F46: Coding Pattern | G46: =IF(E46=TRUE,F46,D46) -> Coding Pattern
A47: ='Ann1 - Step 2'!A47 -> https://github.com/carverauto/serviceradar/blob/main/AGENTS.md | B47: ='Ann1 - Step 2'!B47 -> In migrations, set `prefix: "platform"` for new tables/indexes/constraints and avoid `prefix: "public"` in references. | C47: ='Ann1 - Step 2'!C47 -> Coding Pattern | D47: ='Ann2 - Step 2'!C47 -> Coding Pattern | E47: =IF(C47=D47, FALSE, TRUE) -> FALSE | G47: =IF(E47=TRUE,F47,D47) -> Coding Pattern
A48: ='Ann1 - Step 2'!A48 -> https://github.com/catatsuy/private-isu/blob/master/AGENTS.md | B48: ='Ann1 - Step 2'!B48 -> - Ruby/Python/PHP: follow existing idioms (Ruby 2-space indent, Python PEP 8, PHP PSR-12); avoid mixing tabs and spaces. | C48: ='Ann1 - Step 2'!C48 -> Writing Style Preference | D48: ='Ann2 - Step 2'!C48 -> Coding Pattern | E48: =IF(C48=D48, FALSE, TRUE) -> TRUE | F48: Coding Style | G48: =IF(E48=TRUE,F48,D48) -> Coding Style
A49: ='Ann1 - Step 2'!A49 -> https://github.com/commonwarexyz/monorepo/blob/main/AGENTS.md | B49: ='Ann1 - Step 2'!B49 -> _Avoid building or testing the entire workspace unless absolutely necessary. | C49: ='Ann1 - Step 2'!C49 -> Build & Operation | D49: ='Ann2 - Step 2'!C49 -> Build & Operation | E49: =IF(C49=D49, FALSE, TRUE) -> FALSE | G49: =IF(E49=TRUE,F49,D49) -> Build & Operation
A50: ='Ann1 - Step 2'!A50 -> https://github.com/commonwarexyz/monorepo/blob/main/AGENTS.md | B50: ='Ann1 - Step 2'!B50 -> Avoid `OsRng`, `StdRng::from_entropy()`, or raw `StdRng::seed_from_u64()`. | C50: ='Ann1 - Step 2'!C50 -> Testing | D50: ='Ann2 - Step 2'!C50 -> Coding Pattern | E50: =IF(C50=D50, FALSE, TRUE) -> TRUE | F50: Coding Pattern | G50: =IF(E50=TRUE,F50,D50) -> Coding Pattern
A51: ='Ann1 - Step 2'!A51 -> https://github.com/DannyMac180/meta-agent/blob/main/AGENTS.md | B51: ='Ann1 - Step 2'!B51 -> - Coding Style (TS planned): strict TypeScript, ESLint+Prettier, avoid default exports, prefer functional modules, async/await. | C51: ='Ann1 - Step 2'!C51 -> Coding Style | D51: ='Ann2 - Step 2'!C51 -> Coding Style | E51: =IF(C51=D51, FALSE, TRUE) -> FALSE | G51: =IF(E51=TRUE,F51,D51) -> Coding Style
A52: ='Ann1 - Step 2'!A52 -> https://github.com/epicweb-dev/epicshop/blob/main/AGENTS.md | B52: ='Ann1 - Step 2'!B52 -> - Avoid `@testing-library/react` in browser mode. | C52: ='Ann1 - Step 2'!C52 -> Testing | D52: ='Ann2 - Step 2'!C52 -> Coding Pattern | E52: =IF(C52=D52, FALSE, TRUE) -> TRUE | F52: Testing | G52: =IF(E52=TRUE,F52,D52) -> Testing
A53: ='Ann1 - Step 2'!A53 -> https://github.com/epicweb-dev/epicshop/blob/main/AGENTS.md | B53: ='Ann1 - Step 2'!B53 -> lifecycle and avoids leaking state across tests. | C53: ='Ann1 - Step 2'!C53 -> Testing | D53: ='Ann2 - Step 2'!C53 -> Testing | E53: =IF(C53=D53, FALSE, TRUE) -> FALSE | G53: =IF(E53=TRUE,F53,D53) -> Testing
A54: ='Ann1 - Step 2'!A54 -> https://github.com/epicweb-dev/epicshop/blob/main/AGENTS.md | B54: ='Ann1 - Step 2'!B54 -> - Prefer flat tests with explicit setup to keep intent clear and avoid cascading | C54: ='Ann1 - Step 2'!C54 -> Testing | D54: ='Ann2 - Step 2'!C54 -> Testing | E54: =IF(C54=D54, FALSE, TRUE) -> FALSE | G54: =IF(E54=TRUE,F54,D54) -> Testing
A55: ='Ann1 - Step 2'!A55 -> https://github.com/ESPresense/ESPresense-companion/blob/main/AGENTS.md | B55: ='Ann1 - Step 2'!B55 -> - For local tweaks use `appsettings.json`; avoid hardcoding credentials. | C55: ='Ann1 - Step 2'!C55 -> Security | D55: ='Ann2 - Step 2'!C55 -> Task Execution | E55: =IF(C55=D55, FALSE, TRUE) -> TRUE | F55: Security | G55: =IF(E55=TRUE,F55,D55) -> Security
A56: ='Ann1 - Step 2'!A56 -> https://github.com/gluesql/glues/blob/main/AGENTS.md | B56: ='Ann1 - Step 2'!B56 -> - Default to driving scenarios through real input; avoid mutating internal context (`App::context_mut`) from tests unless absolutely necessary. | C56: ='Ann1 - Step 2'!C56 -> Testing | D56: ='Ann2 - Step 2'!C56 -> Testing | E56: =IF(C56=D56, FALSE, TRUE) -> FALSE | G56: =IF(E56=TRUE,F56,D56) -> Testing
A57: ='Ann1 - Step 2'!A57 -> https://github.com/hahwul/dalfox/blob/main/AGENTS.md | B57: ='Ann1 - Step 2'!B57 -> - MCP is stdio/JSON-RPC; avoid stdout noise in MCP mode (banner/log behavior matters). | C57: ='Ann1 - Step 2'!C57 -> Coding Pattern | D57: ='Ann2 - Step 2'!C57 -> Build & Operation | E57: =IF(C57=D57, FALSE, TRUE) -> TRUE | F57: Coding Pattern | G57: =IF(E57=TRUE,F57,D57) -> Coding Pattern
A58: ='Ann1 - Step 2'!A58 -> https://github.com/hahwul/dalfox/blob/main/AGENTS.md | B58: ='Ann1 - Step 2'!B58 -> - Avoid `unwrap()` in runtime paths where user input or network I/O is involved. | C58: ='Ann1 - Step 2'!C58 -> Coding Pattern | D58: ='Ann2 - Step 2'!C58 -> Coding Pattern | E58: =IF(C58=D58, FALSE, TRUE) -> FALSE | G58: =IF(E58=TRUE,F58,D58) -> Coding Pattern
A59: ='Ann1 - Step 2'!A59 -> https://github.com/janbjorge/pgqueuer/blob/main/AGENTS.md | B59: ='Ann1 - Step 2'!B59 -> - **Avoid `Any`** at nearly all cost. | C59: ='Ann1 - Step 2'!C59 -> Coding Pattern | D59: ='Ann2 - Step 2'!C59 -> Coding Pattern | E59: =IF(C59=D59, FALSE, TRUE) -> FALSE | G59: =IF(E59=TRUE,F59,D59) -> Coding Pattern
A60: ='Ann1 - Step 2'!A60 -> https://github.com/johnlindquist/kit/blob/main/AGENTS.md | B60: ='Ann1 - Step 2'!B60 -> - Env: `.env` supported via `dotenv`/`dotenv-flow`; avoid committing secrets. | C60: ='Ann1 - Step 2'!C60 -> Security | D60: ='Ann2 - Step 2'!C60 -> Security | E60: =IF(C60=D60, FALSE, TRUE) -> FALSE | G60: =IF(E60=TRUE,F60,D60) -> Security
A61: ='Ann1 - Step 2'!A61 -> https://github.com/langfuse/langfuse/blob/main/AGENTS.md | B61: ='Ann1 - Step 2'!B61 -> - Keep changes scoped; avoid unrelated refactors. | C61: ='Ann1 - Step 2'!C61 -> Build & Operation | D61: ='Ann2 - Step 2'!C61 -> Coding Style | E61: =IF(C61=D61, FALSE, TRUE) -> TRUE | F61: Task Execution | G61: =IF(E61=TRUE,F61,D61) -> Task Execution
A62: ='Ann1 - Step 2'!A62 -> https://github.com/luccahuguet/yazelix/blob/main/AGENTS.md | B62: ='Ann1 - Step 2'!B62 -> **Avoid redundant code** - Focus on elegant, concise code when possible; eliminate duplication and unnecessary complexity | C62: ='Ann1 - Step 2'!C62 -> Coding Pattern | D62: ='Ann2 - Step 2'!C62 -> Maintainability | E62: =IF(C62=D62, FALSE, TRUE) -> TRUE | F62: Maintainability | G62: =IF(E62=TRUE,F62,D62) -> Maintainability
A63: ='Ann1 - Step 2'!A63 -> https://github.com/luccahuguet/yazelix/blob/main/AGENTS.md | B63: ='Ann1 - Step 2'!B63 -> These commands require `cargo` and `rustc` on `PATH` and intentionally avoid re-entering `nix develop`. | C63: ='Ann1 - Step 2'!C63 -> Task Execution | D63: ='Ann2 - Step 2'!C63 -> Build & Operation | E63: =IF(C63=D63, FALSE, TRUE) -> TRUE | F63: Build & Operation | G63: =IF(E63=TRUE,F63,D63) -> Build & Operation
A64: ='Ann1 - Step 2'!A64 -> https://github.com/luccahuguet/yazelix/blob/main/AGENTS.md | B64: ='Ann1 - Step 2'!B64 -> - In particular, avoid patterns like arrays of shell lines joined with `str join "\n"` or interpolated multi-line shell snippets whose dynamic values are baked directly into the script text. | C64: ='Ann1 - Step 2'!C64 -> Coding Pattern | D64: ='Ann2 - Step 2'!C64 -> Coding Pattern | E64: =IF(C64=D64, FALSE, TRUE) -> FALSE | G64: =IF(E64=TRUE,F64,D64) -> Coding Pattern
A65: ='Ann1 - Step 2'!A65 -> https://github.com/Pipelex/pipelex/blob/main/AGENTS.md | B65: ='Ann1 - Step 2'!B65 -> Avoid unless using the `exceptiongroup` backport. | C65: ='Ann1 - Step 2'!C65 -> Coding Pattern | D65: ='Ann2 - Step 2'!C65 -> Coding Pattern | E65: =IF(C65=D65, FALSE, TRUE) -> FALSE | G65: =IF(E65=TRUE,F65,D65) -> Coding Pattern
A66: ='Ann1 - Step 2'!A66 -> https://github.com/Pipelex/pipelex/blob/main/AGENTS.md | B66: ='Ann1 - Step 2'!B66 -> - Avoid inline for loops, unless it's ultra-simple and holds on oneline. | C66: ='Ann1 - Step 2'!C66 -> Coding Style | D66: ='Ann2 - Step 2'!C66 -> Coding Pattern | E66: =IF(C66=D66, FALSE, TRUE) -> TRUE | F66: Coding Pattern | G66: =IF(E66=TRUE,F66,D66) -> Coding Pattern
A67: ='Ann1 - Step 2'!A67 -> https://github.com/Pipelex/pipelex/blob/main/AGENTS.md | B67: ='Ann1 - Step 2'!B67 -> - Avoid as much as possible import statements outside of a module's top-level scope. | C67: ='Ann1 - Step 2'!C67 -> Coding Pattern | D67: ='Ann2 - Step 2'!C67 -> Coding Pattern | E67: =IF(C67=D67, FALSE, TRUE) -> FALSE | G67: =IF(E67=TRUE,F67,D67) -> Coding Pattern
A68: ='Ann1 - Step 2'!A68 -> https://github.com/PrairieLearn/PrairieLearn/blob/master/AGENTS.md | B68: ='Ann1 - Step 2'!B68 -> Avoid running the entire test suite unless necessary, as it can be time-consuming. | C68: ='Ann1 - Step 2'!C68 -> Testing | D68: ='Ann2 - Step 2'!C68 -> Testing | E68: =IF(C68=D68, FALSE, TRUE) -> FALSE | G68: =IF(E68=TRUE,F68,D68) -> Testing
A69: ='Ann1 - Step 2'!A69 -> https://github.com/PrairieLearn/PrairieLearn/blob/master/AGENTS.md | B69: ='Ann1 - Step 2'!B69 -> - Avoid unnecessary `useEffect` when using `react-hook-form`. | C69: ='Ann1 - Step 2'!C69 -> Coding Pattern | D69: ='Ann2 - Step 2'!C69 -> Coding Pattern | E69: =IF(C69=D69, FALSE, TRUE) -> FALSE | G69: =IF(E69=TRUE,F69,D69) -> Coding Pattern
A70: ='Ann1 - Step 2'!A70 -> https://github.com/rocketship-ai/rocketship/blob/main/AGENTS.md | B70: ='Ann1 - Step 2'!B70 -> Always include a unique `X-Test-Session` header when calling shared services like `https://tryme.rocketship.sh` to avoid cross-test contamination. | C70: ='Ann1 - Step 2'!C70 -> Build & Operation | D70: ='Ann2 - Step 2'!C70 -> Coding Pattern | E70: =IF(C70=D70, FALSE, TRUE) -> TRUE | F70: Testing | G70: =IF(E70=TRUE,F70,D70) -> Testing
A71: ='Ann1 - Step 2'!A71 -> https://github.com/RSSNext/Folo/blob/main/AGENTS.md | B71: ='Ann1 - Step 2'!B71 -> - TypeScript strict; avoid `any` (use precise types). | C71: ='Ann1 - Step 2'!C71 -> Coding Pattern | D71: ='Ann2 - Step 2'!C71 -> Coding Pattern | E71: =IF(C71=D71, FALSE, TRUE) -> FALSE | G71: =IF(E71=TRUE,F71,D71) -> Coding Pattern
A72: ='Ann1 - Step 2'!A72 -> https://github.com/RSSNext/Folo/blob/main/AGENTS.md | B72: ='Ann1 - Step 2'!B72 -> - **Style extraction**: Avoid inline styles in JSX. | C72: ='Ann1 - Step 2'!C72 -> Coding Pattern | D72: ='Ann2 - Step 2'!C72 -> Coding Style | E72: =IF(C72=D72, FALSE, TRUE) -> TRUE | F72: Coding Style | G72: =IF(E72=TRUE,F72,D72) -> Coding Style
A73: ='Ann1 - Step 2'!A73 -> https://github.com/RSSNext/Folo/blob/main/AGENTS.md | B73: ='Ann1 - Step 2'!B73 -> - Avoid using the `any` type in TypeScript. | C73: ='Ann1 - Step 2'!C73 -> Coding Pattern | D73: ='Ann2 - Step 2'!C73 -> Coding Pattern | E73: =IF(C73=D73, FALSE, TRUE) -> FALSE | G73: =IF(E73=TRUE,F73,D73) -> Coding Pattern
A74: ='Ann1 - Step 2'!A74 -> https://github.com/RSSNext/Folo/blob/main/AGENTS.md | B74: ='Ann1 - Step 2'!B74 -> Avoid conflicting dotted keys. | C74: ='Ann1 - Step 2'!C74 -> Writing Style Preference | D74: ='Ann2 - Step 2'!C74 -> Coding Style | E74: =IF(C74=D74, FALSE, TRUE) -> TRUE | F74: Coding Pattern | G74: =IF(E74=TRUE,F74,D74) -> Coding Pattern
A75: ='Ann1 - Step 2'!A75 -> https://github.com/RSSNext/Folo/blob/main/AGENTS.md | B75: ='Ann1 - Step 2'!B75 -> - Avoid multi-line speculative edits; keep edits minimal and targeted; preserve existing indentation. | C75: ='Ann1 - Step 2'!C75 -> Build & Operation | D75: ='Ann2 - Step 2'!C75 -> Coding Style | E75: =IF(C75=D75, FALSE, TRUE) -> TRUE | F75: Task Execution | G75: =IF(E75=TRUE,F75,D75) -> Task Execution
A76: ='Ann1 - Step 2'!A76 -> https://github.com/rustfs/rustfs/blob/main/AGENTS.md | B76: ='Ann1 - Step 2'!B76 -> - Avoid redundant file reads, repeated commands, and unnecessary exploratory work once enough context is available. | C76: ='Ann1 - Step 2'!C76 -> Task Execution | D76: ='Ann2 - Step 2'!C76 -> Task Execution | E76: =IF(C76=D76, FALSE, TRUE) -> FALSE | G76: =IF(E76=TRUE,F76,D76) -> Task Execution
A77: ='Ann1 - Step 2'!A77 -> https://github.com/rustfs/rustfs/blob/main/AGENTS.md | B77: ='Ann1 - Step 2'!B77 -> Avoid sycophantic openers, closing fluff, and verbose status reporting. | C77: ='Ann1 - Step 2'!C77 -> Documentation | D77: ='Ann2 - Step 2'!C77 -> Writing Style Preference | E77: =IF(C77=D77, FALSE, TRUE) -> TRUE | F77: Writing Style Preference | G77: =IF(E77=TRUE,F77,D77) -> Writing Style Preference
A78: ='Ann1 - Step 2'!A78 -> https://github.com/rustfs/rustfs/blob/main/AGENTS.md | B78: ='Ann1 - Step 2'!B78 -> - Keep fixes narrowly aligned with the requested behavior; avoid semantic-adjacent rewrites while touching sensitive paths. | C78: ='Ann1 - Step 2'!C78 -> Coding Pattern | D78: ='Ann2 - Step 2'!C78 -> Coding Style | E78: =IF(C78=D78, FALSE, TRUE) -> TRUE | F78: Task Execution | G78: =IF(E78=TRUE,F78,D78) -> Task Execution
A79: ='Ann1 - Step 2'!A79 -> https://github.com/rustfs/rustfs/blob/main/AGENTS.md | B79: ='Ann1 - Step 2'!B79 -> - If a new string is truly unique, define a local constant near related logic and avoid scattering the literal across multiple sites. | C79: ='Ann1 - Step 2'!C79 -> Writing Style Preference | D79: ='Ann2 - Step 2'!C79 -> Coding Pattern | E79: =IF(C79=D79, FALSE, TRUE) -> TRUE | F79: Coding Pattern | G79: =IF(E79=TRUE,F79,D79) -> Coding Pattern
A80: ='Ann1 - Step 2'!A80 -> https://github.com/rustfs/rustfs/blob/main/AGENTS.md | B80: ='Ann1 - Step 2'!B80 -> Avoid duplicating long crate lists or command matrices in instruction files. | C80: ='Ann1 - Step 2'!C80 -> Coding Pattern | D80: ='Ann2 - Step 2'!C80 -> Task Execution | E80: =IF(C80=D80, FALSE, TRUE) -> TRUE | F80: Documentation | G80: =IF(E80=TRUE,F80,D80) -> Documentation
A81: ='Ann1 - Step 2'!A81 -> https://github.com/seasonedcc/remix-forms/blob/main/AGENTS.md | B81: ='Ann1 - Step 2'!B81 -> Avoid checking Tailwind classes, CSS, or which specific HTML tag is rendered. | C81: ='Ann1 - Step 2'!C81 -> Testing | D81: ='Ann2 - Step 2'!C81 -> Testing | E81: =IF(C81=D81, FALSE, TRUE) -> FALSE | G81: =IF(E81=TRUE,F81,D81) -> Testing
A82: ='Ann1 - Step 2'!A82 -> https://github.com/seasonedcc/remix-forms/blob/main/AGENTS.md | B82: ='Ann1 - Step 2'!B82 -> Avoid catch‑all labels like "additional tests". | C82: ='Ann1 - Step 2'!C82 -> Testing | D82: ='Ann2 - Step 2'!C82 -> Testing | E82: =IF(C82=D82, FALSE, TRUE) -> FALSE | G82: =IF(E82=TRUE,F82,D82) -> Testing
A83: ='Ann1 - Step 2'!A83 -> https://github.com/stack-auth/stack-auth/blob/main/AGENTS.md | B83: ='Ann1 - Step 2'!B83 -> - Try to avoid the `any` type. | C83: ='Ann1 - Step 2'!C83 -> Coding Pattern | D83: ='Ann2 - Step 2'!C83 -> Coding Pattern | E83: =IF(C83=D83, FALSE, TRUE) -> FALSE | G83: =IF(E83=TRUE,F83,D83) -> Coding Pattern
A84: ='Ann1 - Step 2'!A84 -> https://github.com/stack-auth/stack-auth/blob/main/AGENTS.md | B84: ='Ann1 - Step 2'!B84 -> Avoid wherever possible. | C84: ='Ann1 - Step 2'!C84 -> Coding Pattern | D84: ='Ann2 - Step 2'!C84 -> Coding Pattern | E84: =IF(C84=D84, FALSE, TRUE) -> FALSE | G84: =IF(E84=TRUE,F84,D84) -> Coding Pattern
A85: ='Ann1 - Step 2'!A85 -> https://github.com/swarmauri/swarmauri-sdk/blob/main/AGENTS.md | B85: ='Ann1 - Step 2'!B85 -> avoid using the ``PluginManager`` unless explicitly directed otherwise. | C85: ='Ann1 - Step 2'!C85 -> Build & Operation | D85: ='Ann2 - Step 2'!C85 -> Coding Pattern | E85: =IF(C85=D85, FALSE, TRUE) -> TRUE | F85: Coding Pattern | G85: =IF(E85=TRUE,F85,D85) -> Coding Pattern
A86: ='Ann1 - Step 2'!A86 -> https://github.com/useautumn/autumn/blob/main/AGENTS.md | B86: ='Ann1 - Step 2'!B86 -> - Any new or refactored runtime balance/reset/cache patch code should continue following this policy and avoid adding new cache-version bumps by default. | C86: ='Ann1 - Step 2'!C86 -> Build & Operation | D86: ='Ann2 - Step 2'!C86 -> Performance | E86: =IF(C86=D86, FALSE, TRUE) -> TRUE | F86: Coding Pattern | G86: =IF(E86=TRUE,F86,D86) -> Coding Pattern
A87: ='Ann1 - Step 2'!A87 -> https://github.com/web-infra-dev/rspack/blob/main/AGENTS.md | B87: ='Ann1 - Step 2'!B87 -> - **Rust**: Core in `crates/rspack_core/`, plugins in `crates/rspack_plugin_*/`, rebuild with `pnpm run build:binding:dev`, test with `pnpm run test:rs`, avoid linting and formatting for fast local development | C87: ='Ann1 - Step 2'!C87 -> Build & Operation | D87: ='Ann2 - Step 2'!C87 -> Coding Style | E87: =IF(C87=D87, FALSE, TRUE) -> TRUE | F87: Build & Operation | G87: =IF(E87=TRUE,F87,D87) -> Build & Operation
A88: ='Ann1 - Step 2'!A88 -> https://github.com/webgptorg/promptbook/blob/main/AGENTS.md | B88: ='Ann1 - Step 2'!B88 -> - Keep small responsibilities of functions and classes, avoid creating big functions or classes that do many things. | C88: ='Ann1 - Step 2'!C88 -> Coding Pattern | D88: ='Ann2 - Step 2'!C88 -> Coding Pattern | E88: =IF(C88=D88, FALSE, TRUE) -> FALSE | G88: =IF(E88=TRUE,F88,D88) -> Coding Pattern
A89: ='Ann1 - Step 2'!A89 -> https://github.com/wieslawsoltes/Dock/blob/master/AGENTS.md | B89: ='Ann1 - Step 2'!B89 -> - Open/Closed: extend behavior via composition and interfaces; avoid modifying | C89: ='Ann1 - Step 2'!C89 -> Coding Pattern | D89: ='Ann2 - Step 2'!C89 -> Task Execution | E89: =IF(C89=D89, FALSE, TRUE) -> TRUE | F89: Coding Pattern | G89: =IF(E89=TRUE,F89,D89) -> Coding Pattern
A90: ='Ann1 - Step 2'!A90 -> https://github.com/wieslawsoltes/Dock/blob/master/AGENTS.md | B90: ='Ann1 - Step 2'!B90 -> - Interface Segregation: prefer small, focused interfaces; avoid "god" interfaces. | C90: ='Ann1 - Step 2'!C90 -> Coding Pattern | D90: ='Ann2 - Step 2'!C90 -> Coding Pattern | E90: =IF(C90=D90, FALSE, TRUE) -> FALSE | G90: =IF(E90=TRUE,F90,D90) -> Coding Pattern
A91: ='Ann1 - Step 2'!A91 -> https://github.com/wieslawsoltes/Dock/blob/master/AGENTS.md | B91: ='Ann1 - Step 2'!B91 -> - Use XAML for layout and visuals; avoid creating controls in code. | C91: ='Ann1 - Step 2'!C91 -> Writing Style Preference | D91: ='Ann2 - Step 2'!C91 -> Task Execution | E91: =IF(C91=D91, FALSE, TRUE) -> TRUE | F91: Coding Pattern | G91: =IF(E91=TRUE,F91,D91) -> Coding Pattern
A92: ='Ann1 - Step 2'!A92 -> https://github.com/wieslawsoltes/Dock/blob/master/AGENTS.md | B92: ='Ann1 - Step 2'!B92 -> - Avoid LINQ in hot paths; use loops and pre-sized collections. | C92: ='Ann1 - Step 2'!C92 -> Performance | D92: ='Ann2 - Step 2'!C92 -> Coding Pattern | E92: =IF(C92=D92, FALSE, TRUE) -> TRUE | F92: Performance | G92: =IF(E92=TRUE,F92,D92) -> Performance
A93: ='Ann1 - Step 2'!A93 -> https://github.com/wieslawsoltes/Dock/blob/master/AGENTS.md | B93: ='Ann1 - Step 2'!B93 -> - Minimize boxing, virtual dispatch in tight loops, and avoid unnecessary | C93: ='Ann1 - Step 2'!C93 -> Performance | D93: ='Ann2 - Step 2'!C93 -> Performance | E93: =IF(C93=D93, FALSE, TRUE) -> FALSE | G93: =IF(E93=TRUE,F93,D93) -> Performance
A94: ='Ann1 - Step 2'!A94 -> https://github.com/wieslawsoltes/Dock/blob/master/AGENTS.md | B94: ='Ann1 - Step 2'!B94 -> - Avoid static state (except truly immutable constants). | C94: ='Ann1 - Step 2'!C94 -> Coding Pattern | D94: ='Ann2 - Step 2'!C94 -> Coding Pattern | E94: =IF(C94=D94, FALSE, TRUE) -> FALSE | G94: =IF(E94=TRUE,F94,D94) -> Coding Pattern
A95: ='Ann1 - Step 2'!A95 -> https://github.com/wieslawsoltes/Dock/blob/master/AGENTS.md | B95: ='Ann1 - Step 2'!B95 -> - Prefer explicit types where clarity is improved; avoid `var` in public APIs. | C95: ='Ann1 - Step 2'!C95 -> Coding Pattern | D95: ='Ann2 - Step 2'!C95 -> Coding Pattern | E95: =IF(C95=D95, FALSE, TRUE) -> FALSE | G95: =IF(E95=TRUE,F95,D95) -> Coding Pattern
A96: ='Ann1 - Step 2'!A96 -> https://github.com/wieslawsoltes/Xaml.Behaviors/blob/master/AGENTS.md | B96: ='Ann1 - Step 2'!B96 -> - Open/Closed: extend behavior via composition and interfaces; avoid modifying | C96: ='Ann1 - Step 2'!C96 -> Coding Pattern | D96: ='Ann2 - Step 2'!C96 -> Task Execution | E96: =IF(C96=D96, FALSE, TRUE) -> TRUE | F96: Coding Pattern | G96: =IF(E96=TRUE,F96,D96) -> Coding Pattern
A97: ='Ann1 - Step 2'!A97 -> https://github.com/wieslawsoltes/Xaml.Behaviors/blob/master/AGENTS.md | B97: ='Ann1 - Step 2'!B97 -> - Interface Segregation: prefer small, focused interfaces; avoid "god" interfaces. | C97: ='Ann1 - Step 2'!C97 -> Coding Pattern | D97: ='Ann2 - Step 2'!C97 -> Coding Pattern | E97: =IF(C97=D97, FALSE, TRUE) -> FALSE | G97: =IF(E97=TRUE,F97,D97) -> Coding Pattern
A98: ='Ann1 - Step 2'!A98 -> https://github.com/wieslawsoltes/Xaml.Behaviors/blob/master/AGENTS.md | B98: ='Ann1 - Step 2'!B98 -> - Use XAML for layout and visuals; avoid creating controls in code. | C98: ='Ann1 - Step 2'!C98 -> Writing Style Preference | D98: ='Ann2 - Step 2'!C98 -> Coding Pattern | E98: =IF(C98=D98, FALSE, TRUE) -> TRUE | F98: Coding Pattern | G98: =IF(E98=TRUE,F98,D98) -> Coding Pattern
A99: ='Ann1 - Step 2'!A99 -> https://github.com/wieslawsoltes/Xaml.Behaviors/blob/master/AGENTS.md | B99: ='Ann1 - Step 2'!B99 -> - Prefer `DirectProperty` for non-styled properties to avoid extra overhead. | C99: ='Ann1 - Step 2'!C99 -> Coding Pattern | D99: ='Ann2 - Step 2'!C99 -> Performance | E99: =IF(C99=D99, FALSE, TRUE) -> TRUE | F99: Performance | G99: =IF(E99=TRUE,F99,D99) -> Performance
A100: ='Ann1 - Step 2'!A100 -> https://github.com/wieslawsoltes/Xaml.Behaviors/blob/master/AGENTS.md | B100: ='Ann1 - Step 2'!B100 -> - Avoid LINQ in hot paths; use loops and pre-sized collections. | C100: ='Ann1 - Step 2'!C100 -> Performance | D100: ='Ann2 - Step 2'!C100 -> Coding Pattern | E100: =IF(C100=D100, FALSE, TRUE) -> TRUE | F100: Performance | G100: =IF(E100=TRUE,F100,D100) -> Performance
...

Sheet Step2 Stats
A1: Ann1 | B1: Ann2 | D1: N | E1: =COUNTA(A2:A2462) -> 500
A2: Testing | B2: Testing | D2: Observed agreement | E2: =SUMPRODUCT((A2:A2462<>"")*(A2:A2462=B2:B2462))/E1 -> 0.552 | G2: =IFERROR(__xludf.DUMMYFUNCTION("SORT(UNIQUE(FILTER({A2:A2462;B2:B2462},{A2:A2462;B2:B2462}<>"""")))"),"Build & Operation") -> Build & Operation | H2: {=IF(G2:G2462="",,COUNTIF($A$2:$A2462,G2:G2462)/$E$1)} -> 0.084 | I2: {=IF(G2:G2462="",,COUNTIF($B$2:$B2462,G2:G2462)/$E$1)} -> 0.072 | J2: {=IF(G2:G2462="",,H2:H2462*I2:I2462)} -> 0.006048
A3: Task Execution | B3: Coding Pattern | D3: Expected agreement | E3: =SUM(J2:J2462) -> 0.1504 | G3: =IFERROR(__xludf.DUMMYFUNCTION("""COMPUTED_VALUE"""),"Code Review") -> Code Review | H3: 0.012 | I3: 0.012 | J3: 0.000144
A4: Documentation | B4: Documentation | D4: Cohen’s κ | E4: =IF(1-E3=0,"Kappa undefined",(E2-E3)/(1-E3)) -> 0.47269303 | G4: =IFERROR(__xludf.DUMMYFUNCTION("""COMPUTED_VALUE"""),"Coding Pattern") -> Coding Pattern | H4: 0.284 | I4: 0.334 | J4: 0.094856
A5: Coding Style | B5: Coding Pattern | G5: =IFERROR(__xludf.DUMMYFUNCTION("""COMPUTED_VALUE"""),"Coding Style") -> Coding Style | H5: 0.066 | I5: 0.06 | J5: 0.00396
A6: Commit&PR rule | B6: Commit&PR rule | G6: =IFERROR(__xludf.DUMMYFUNCTION("""COMPUTED_VALUE"""),"Commit&PR rule") -> Commit&PR rule | H6: 0.086 | I6: 0.078 | J6: 0.006708
A7: Build & Operation | B7: Documentation | G7: =IFERROR(__xludf.DUMMYFUNCTION("""COMPUTED_VALUE"""),"Documentation") -> Documentation | H7: 0.096 | I7: 0.096 | J7: 0.009216
A8: Coding Style | B8: Coding Pattern | G8: =IFERROR(__xludf.DUMMYFUNCTION("""COMPUTED_VALUE"""),"Maintainability") -> Maintainability | H8: 0.058 | I8: 0.022 | J8: 0.001276
A9: Commit&PR rule | B9: Commit&PR rule | G9: =IFERROR(__xludf.DUMMYFUNCTION("""COMPUTED_VALUE"""),"Other") -> Other | H9: 0 | I9: 0.004 | J9: 0
A10: Coding Style | B10: Coding Style | G10: =IFERROR(__xludf.DUMMYFUNCTION("""COMPUTED_VALUE"""),"Performance") -> Performance | H10: 0.05 | I10: 0.018 | J10: 0.0009
A11: Coding Style | B11: Coding Pattern | G11: =IFERROR(__xludf.DUMMYFUNCTION("""COMPUTED_VALUE"""),"Security") -> Security | H11: 0.022 | I11: 0.02 | J11: 0.00044
A12: Testing | B12: Testing | G12: =IFERROR(__xludf.DUMMYFUNCTION("""COMPUTED_VALUE"""),"Task Execution") -> Task Execution | H12: 0.104 | I12: 0.16 | J12: 0.01664
A13: Coding Style | B13: Coding Pattern | G13: =IFERROR(__xludf.DUMMYFUNCTION("""COMPUTED_VALUE"""),"Testing") -> Testing | H13: 0.092 | I13: 0.098 | J13: 0.009016
A14: Commit&PR rule | B14: Commit&PR rule | G14: =IFERROR(__xludf.DUMMYFUNCTION("""COMPUTED_VALUE"""),"Writing Style Preference") -> Writing Style Preference | H14: 0.046 | I14: 0.026 | J14: 0.001196
A15: Coding Style | B15: Coding Pattern | H15: 0 | I15: 0 | J15: 0
A16: Coding Style | B16: Coding Pattern | H16: 0 | I16: 0 | J16: 0
A17: Maintainability | B17: Coding Pattern | H17: 0 | I17: 0 | J17: 0
A18: Testing | B18: Testing | H18: 0 | I18: 0 | J18: 0
A19: Coding Style | B19: Coding Pattern | H19: 0 | I19: 0 | J19: 0
A20: Maintainability | B20: Testing | H20: 0 | I20: 0 | J20: 0
A21: Maintainability | B21: Testing | H21: 0 | I21: 0 | J21: 0
A22: Testing | B22: Coding Style | H22: 0 | I22: 0 | J22: 0
A23: Coding Style | B23: Coding Pattern | H23: 0 | I23: 0 | J23: 0
A24: Coding Pattern | B24: Coding Pattern | H24: 0 | I24: 0 | J24: 0
A25: Coding Pattern | B25: Commit&PR rule | H25: 0 | I25: 0 | J25: 0
A26: Coding Pattern | B26: Coding Pattern | H26: 0 | I26: 0 | J26: 0
... A501: Task Execution | B501: Task Execution | H501: 0 | I501: 0 | J501: 0
H502: 0 | I502: 0 | J502: 0
H503: 0 | I503: 0 | J503: 0
H504: 0 | I504: 0 | J504: 0
H505: 0 | I505: 0 | J505: 0
H506: 0 | I506: 0 | J506: 0
H507: 0 | I507: 0 | J507: 0
H508: 0 | I508: 0 | J508: 0
H509: 0 | I509: 0 | J509: 0
H510: 0 | I510: 0 | J510: 0
H511: 0 | I511: 0 | J511: 0
H512: 0 | I512: 0 | J512: 0
H513: 0 | I513: 0 | J513: 0
... H2462: 0 | I2462: 0 | J2462: 0

Sheet Ann1 - Step 3
A1: Column 3 | B1: Instruction | C1: Category | D1: Exist in other sheets
A2: https://github.com/marin-community/marin/blob/main/AGENTS.md | B2: Do not restate the code. | C2: Documentation | D2: 0
A3: https://github.com/marin-community/marin/blob/main/AGENTS.md | B3: Do not create parallel implementations. | C3: Coding Pattern | D3: 0
A4: https://github.com/marin-community/marin/blob/main/AGENTS.md | B4: Do not relax tolerances or hack around failures. | C4: Testing | D4: 0
A5: https://github.com/microsoft/mcp-for-beginners/blob/main/AGENTS.md | B5: - **translations/**: Language-specific versions (auto-generated, do not edit directly) | C5: Documentation | D5: 0
A6: https://github.com/microsoft/mcp-for-beginners/blob/main/AGENTS.md | B6: - **Do NOT manually edit** files in `translations/` directory | C6: Documentation | D6: 0
A7: https://github.com/microsoft/mcp-for-beginners/blob/main/AGENTS.md | B7: - Do not directly edit files in `translations/` directory | C7: Documentation | D7: 0
A8: https://github.com/microsoft/mcp-for-beginners/blob/main/AGENTS.md | B8: - Do not edit `translated_images/` directory | C8: Documentation | D8: 0
A9: https://github.com/msgbyte/tianji/blob/master/AGENTS.md | B9: When generating code, **do not modify** any JSON files in `src/client/public/locales`. | C9: Task Execution | D9: 0
A10: https://github.com/openai/openai-agents-python/blob/main/AGENTS.md | B10: Do not treat branch-local interface churn or unreleased post-tag changes on `main` as breaking by default; prefer direct replacement over compatibility layers in those cases, and renumber or squash unreleased persisted schemas before release when the intermediate snapshots are intentionally unsupported. | C10: Commit&PR rule | D10: 1
A11: https://github.com/openai/openai-agents-python/blob/main/AGENTS.md | B11: Do not insert new constructor parameters or dataclass fields in the middle of existing public order. | C11: Coding Pattern | D11: 1
A12: https://github.com/openai/openai-agents-python/blob/main/AGENTS.md | B12: - Prefer keyword arguments at call sites to reduce accidental breakage, but do not rely on this to justify breaking positional compatibility for public APIs. | C12: Coding Pattern | D12: 1
A13: https://github.com/openai/openai-agents-python/blob/main/AGENTS.md | B13: - `docs/`: MkDocs documentation source; do not edit translated docs under `docs/ja`, `docs/ko`, or `docs/zh` (they are generated). | C13: Documentation | D13: 1
... A1943: https://github.com/dailydotdev/apps/blob/main/CLAUDE.md | B1943: - ❌ **Wrong**: Local `stripHtml()` in webapp-only file | C1943: Coding Pattern | D1943: 0

Sheet Ann2 - Step 3
A1: Column 3 | B1: Instruction | C1: Category | D1: Exist in other sheets
A2: https://github.com/marin-community/marin/blob/main/AGENTS.md | B2: Do not restate the code. | C2: Documentation | D2: 0
A3: https://github.com/marin-community/marin/blob/main/AGENTS.md | B3: Do not create parallel implementations. | C3: Coding Pattern | D3: 0
A4: https://github.com/marin-community/marin/blob/main/AGENTS.md | B4: Do not relax tolerances or hack around failures. | C4: Testing | D4: 0
A5: https://github.com/microsoft/mcp-for-beginners/blob/main/AGENTS.md | B5: - **translations/**: Language-specific versions (auto-generated, do not edit directly) | C5: Documentation | D5: 0
A6: https://github.com/microsoft/mcp-for-beginners/blob/main/AGENTS.md | B6: - **Do NOT manually edit** files in `translations/` directory | C6: Documentation | D6: 0
A7: https://github.com/microsoft/mcp-for-beginners/blob/main/AGENTS.md | B7: - Do not directly edit files in `translations/` directory | C7: Documentation | D7: 0
A8: https://github.com/microsoft/mcp-for-beginners/blob/main/AGENTS.md | B8: - Do not edit `translated_images/` directory | C8: Documentation | D8: 0
A9: https://github.com/msgbyte/tianji/blob/master/AGENTS.md | B9: When generating code, **do not modify** any JSON files in `src/client/public/locales`. | C9: Task Execution | D9: 0
A10: https://github.com/openai/openai-agents-python/blob/main/AGENTS.md | B10: Do not treat branch-local interface churn or unreleased post-tag changes on `main` as breaking by default; prefer direct replacement over compatibility layers in those cases, and renumber or squash unreleased persisted schemas before release when the intermediate snapshots are intentionally unsupported. | C10: Commit&PR rule | D10: 1
A11: https://github.com/openai/openai-agents-python/blob/main/AGENTS.md | B11: Do not insert new constructor parameters or dataclass fields in the middle of existing public order. | C11: Coding Pattern | D11: 1
A12: https://github.com/openai/openai-agents-python/blob/main/AGENTS.md | B12: - Prefer keyword arguments at call sites to reduce accidental breakage, but do not rely on this to justify breaking positional compatibility for public APIs. | C12: Coding Pattern | D12: 1
A13: https://github.com/openai/openai-agents-python/blob/main/AGENTS.md | B13: - `docs/`: MkDocs documentation source; do not edit translated docs under `docs/ja`, `docs/ko`, or `docs/zh` (they are generated). | C13: Documentation | D13: 1
... A1943: https://github.com/dailydotdev/apps/blob/main/CLAUDE.md | B1943: - ❌ **Wrong**: Local `stripHtml()` in webapp-only file | C1943: Coding Pattern | D1943: 0

Sheet Step3 Merge
A1: Column 3 | B1: Instruction | C1: Ann1 | D1: Ann2 | F1: Final
A2: https://github.com/marin-community/marin/blob/main/AGENTS.md | B2: Do not restate the code. | C2: ='Ann1 - Step 3'!C2 -> Documentation | D2: ='Ann2 - Step 3'!C2 -> Documentation | E2: =IF(C2=D2, FALSE, TRUE) -> FALSE | G2: =IF(E2=TRUE,F2,D2) -> Documentation
A3: https://github.com/marin-community/marin/blob/main/AGENTS.md | B3: Do not create parallel implementations. | C3: ='Ann1 - Step 3'!C3 -> Coding Pattern | D3: ='Ann2 - Step 3'!C3 -> Coding Pattern | E3: =IF(C3=D3, FALSE, TRUE) -> FALSE | G3: =IF(E3=TRUE,F3,D3) -> Coding Pattern
A4: https://github.com/marin-community/marin/blob/main/AGENTS.md | B4: Do not relax tolerances or hack around failures. | C4: ='Ann1 - Step 3'!C4 -> Testing | D4: ='Ann2 - Step 3'!C4 -> Testing | E4: =IF(C4=D4, FALSE, TRUE) -> FALSE | G4: =IF(E4=TRUE,F4,D4) -> Testing
A5: https://github.com/microsoft/mcp-for-beginners/blob/main/AGENTS.md | B5: - **translations/**: Language-specific versions (auto-generated, do not edit directly) | C5: ='Ann1 - Step 3'!C5 -> Documentation | D5: ='Ann2 - Step 3'!C5 -> Documentation | E5: =IF(C5=D5, FALSE, TRUE) -> FALSE | G5: =IF(E5=TRUE,F5,D5) -> Documentation
A6: https://github.com/microsoft/mcp-for-beginners/blob/main/AGENTS.md | B6: - **Do NOT manually edit** files in `translations/` directory | C6: ='Ann1 - Step 3'!C6 -> Documentation | D6: ='Ann2 - Step 3'!C6 -> Documentation | E6: =IF(C6=D6, FALSE, TRUE) -> FALSE | G6: =IF(E6=TRUE,F6,D6) -> Documentation
A7: https://github.com/microsoft/mcp-for-beginners/blob/main/AGENTS.md | B7: - Do not directly edit files in `translations/` directory | C7: ='Ann1 - Step 3'!C7 -> Documentation | D7: ='Ann2 - Step 3'!C7 -> Documentation | E7: =IF(C7=D7, FALSE, TRUE) -> FALSE | G7: =IF(E7=TRUE,F7,D7) -> Documentation
A8: https://github.com/microsoft/mcp-for-beginners/blob/main/AGENTS.md | B8: - Do not edit `translated_images/` directory | C8: ='Ann1 - Step 3'!C8 -> Documentation | D8: ='Ann2 - Step 3'!C8 -> Documentation | E8: =IF(C8=D8, FALSE, TRUE) -> FALSE | G8: =IF(E8=TRUE,F8,D8) -> Documentation
A9: https://github.com/msgbyte/tianji/blob/master/AGENTS.md | B9: When generating code, **do not modify** any JSON files in `src/client/public/locales`. | C9: ='Ann1 - Step 3'!C9 -> Task Execution | D9: ='Ann2 - Step 3'!C9 -> Task Execution | E9: =IF(C9=D9, FALSE, TRUE) -> FALSE | G9: =IF(E9=TRUE,F9,D9) -> Task Execution
A10: https://github.com/openai/openai-agents-python/blob/main/AGENTS.md | B10: Do not treat branch-local interface churn or unreleased post-tag changes on `main` as breaking by default; prefer direct replacement over compatibility layers in those cases, and renumber or squash unreleased persisted schemas before release when the intermediate snapshots are intentionally unsupported. | C10: ='Ann1 - Step 3'!C10 -> Commit&PR rule | D10: ='Ann2 - Step 3'!C10 -> Commit&PR rule | E10: =IF(C10=D10, FALSE, TRUE) -> FALSE | G10: =IF(E10=TRUE,F10,D10) -> Commit&PR rule
A11: https://github.com/openai/openai-agents-python/blob/main/AGENTS.md | B11: Do not insert new constructor parameters or dataclass fields in the middle of existing public order. | C11: ='Ann1 - Step 3'!C11 -> Coding Pattern | D11: ='Ann2 - Step 3'!C11 -> Coding Pattern | E11: =IF(C11=D11, FALSE, TRUE) -> FALSE | G11: =IF(E11=TRUE,F11,D11) -> Coding Pattern
A12: https://github.com/openai/openai-agents-python/blob/main/AGENTS.md | B12: - Prefer keyword arguments at call sites to reduce accidental breakage, but do not rely on this to justify breaking positional compatibility for public APIs. | C12: ='Ann1 - Step 3'!C12 -> Coding Pattern | D12: ='Ann2 - Step 3'!C12 -> Coding Pattern | E12: =IF(C12=D12, FALSE, TRUE) -> FALSE | G12: =IF(E12=TRUE,F12,D12) -> Coding Pattern
A13: https://github.com/openai/openai-agents-python/blob/main/AGENTS.md | B13: - `docs/`: MkDocs documentation source; do not edit translated docs under `docs/ja`, `docs/ko`, or `docs/zh` (they are generated). | C13: ='Ann1 - Step 3'!C13 -> Documentation | D13: ='Ann2 - Step 3'!C13 -> Documentation | E13: =IF(C13=D13, FALSE, TRUE) -> FALSE | G13: =IF(E13=TRUE,F13,D13) -> Documentation
... A38: https://github.com/pulumi/docs/blob/master/AGENTS.md | B38: - Mirror the structure of existing content; do not invent new layouts. | C38: ='Ann1 - Step 3'!C38 -> Documentation | D38: ='Ann2 - Step 3'!C38 -> Documentation | E38: =IF(C38=D38, FALSE, TRUE) -> FALSE | G38: =IF(E38=TRUE,F38,D38) -> Documentation
A39: https://github.com/pulumi/docs/blob/master/AGENTS.md | B39: - **DO NOT update links in**: | C39: ='Ann1 - Step 3'!C39 -> Documentation | D39: ='Ann2 - Step 3'!C39 -> Task Execution | E39: =IF(C39=D39, FALSE, TRUE) -> TRUE | F39: Documentation | G39: =IF(E39=TRUE,F39,D39) -> Documentation
A40: https://github.com/python-cachier/cachier/blob/master/AGENTS.md | B40: - **Do not emit warnings/errors for missing optional deps at import time.** | C40: ='Ann1 - Step 3'!C40 -> Coding Pattern | D40: ='Ann2 - Step 3'!C40 -> Coding Pattern | E40: =IF(C40=D40, FALSE, TRUE) -> FALSE | G40: =IF(E40=TRUE,F40,D40) -> Coding Pattern
A41: https://github.com/pytorch/pytorch/blob/main/AGENTS.md | B41: Do not commit files from this directory. | C41: ='Ann1 - Step 3'!C41 -> Commit&PR rule | D41: ='Ann2 - Step 3'!C41 -> Commit&PR rule | E41: =IF(C41=D41, FALSE, TRUE) -> FALSE | G41: =IF(E41=TRUE,F41,D41) -> Commit&PR rule
A42: https://github.com/pytorch/pytorch/blob/main/AGENTS.md | B42: Do NOT try to find alternatives or install these tools. | C42: ='Ann1 - Step 3'!C42 -> Build & Operation | D42: ='Ann2 - Step 3'!C42 -> Build & Operation | E42: =IF(C42=D42, FALSE, TRUE) -> FALSE | G42: =IF(E42=TRUE,F42,D42) -> Build & Operation
A43: https://github.com/pytorch/pytorch/blob/main/AGENTS.md | B43: Do not make changes | C43: ='Ann1 - Step 3'!C43 -> Task Execution | D43: ='Ann2 - Step 3'!C43 -> Build & Operation | E43: =IF(C43=D43, FALSE, TRUE) -> TRUE | F43: Task Execution | G43: =IF(E43=TRUE,F43,D43) -> Task Execution
A44: https://github.com/pytorch/pytorch/blob/main/AGENTS.md | B44: Do not introduce Unicode characters | C44: ='Ann1 - Step 3'!C44 -> Coding Style | D44: ='Ann2 - Step 3'!C44 -> Coding Style | E44: =IF(C44=D44, FALSE, TRUE) -> FALSE | G44: =IF(E44=TRUE,F44,D44) -> Coding Style
A45: https://github.com/Rello/analytics/blob/master/AGENTS.md | B45: | Do not modify | | C45: ='Ann1 - Step 3'!C45 -> Task Execution | D45: ='Ann2 - Step 3'!C45 -> Task Execution | E45: =IF(C45=D45, FALSE, TRUE) -> FALSE | G45: =IF(E45=TRUE,F45,D45) -> Task Execution
A46: https://github.com/Rello/analytics/blob/master/AGENTS.md | B46: | Do not modify | | C46: ='Ann1 - Step 3'!C46 -> Task Execution | D46: ='Ann2 - Step 3'!C46 -> Task Execution | E46: =IF(C46=D46, FALSE, TRUE) -> FALSE | G46: =IF(E46=TRUE,F46,D46) -> Task Execution
A47: https://github.com/Rello/analytics/blob/master/AGENTS.md | B47: | Do not modify | | C47: ='Ann1 - Step 3'!C47 -> Task Execution | D47: ='Ann2 - Step 3'!C47 -> Task Execution | E47: =IF(C47=D47, FALSE, TRUE) -> FALSE | G47: =IF(E47=TRUE,F47,D47) -> Task Execution
A48: https://github.com/Rello/analytics/blob/master/AGENTS.md | B48: | Do not modify | | C48: ='Ann1 - Step 3'!C48 -> Task Execution | D48: ='Ann2 - Step 3'!C48 -> Task Execution | E48: =IF(C48=D48, FALSE, TRUE) -> FALSE | G48: =IF(E48=TRUE,F48,D48) -> Task Execution
A49: https://github.com/Rello/analytics/blob/master/AGENTS.md | B49: Do not use ILogger. | C49: ='Ann1 - Step 3'!C49 -> Coding Pattern | D49: ='Ann2 - Step 3'!C49 -> Coding Pattern | E49: =IF(C49=D49, FALSE, TRUE) -> FALSE | G49: =IF(E49=TRUE,F49,D49) -> Coding Pattern
A50: https://github.com/Rello/audioplayer/blob/master/AGENTS.md | B50: | Do not modify | | C50: ='Ann1 - Step 3'!C50 -> Task Execution | D50: ='Ann2 - Step 3'!C50 -> Task Execution | E50: =IF(C50=D50, FALSE, TRUE) -> FALSE | G50: =IF(E50=TRUE,F50,D50) -> Task Execution
A51: https://github.com/Rello/audioplayer/blob/master/AGENTS.md | B51: | Do not modify | | C51: ='Ann1 - Step 3'!C51 -> Task Execution | D51: ='Ann2 - Step 3'!C51 -> Task Execution | E51: =IF(C51=D51, FALSE, TRUE) -> FALSE | G51: =IF(E51=TRUE,F51,D51) -> Task Execution
A52: https://github.com/Rello/audioplayer/blob/master/AGENTS.md | B52: | Do not modify | | C52: ='Ann1 - Step 3'!C52 -> Task Execution | D52: ='Ann2 - Step 3'!C52 -> Task Execution | E52: =IF(C52=D52, FALSE, TRUE) -> FALSE | G52: =IF(E52=TRUE,F52,D52) -> Task Execution
A53: https://github.com/rocketship-ai/rocketship/blob/main/AGENTS.md | B53: Optimise for the current epic even if it means breaking past behaviour; do not preserve legacy code paths for compatibility unless the user explicitly asks. | C53: ='Ann1 - Step 3'!C53 -> Maintainability | D53: ='Ann2 - Step 3'!C53 -> Maintainability | E53: =IF(C53=D53, FALSE, TRUE) -> FALSE | G53: =IF(E53=TRUE,F53,D53) -> Maintainability
A54: https://github.com/rocketship-ai/rocketship/blob/main/AGENTS.md | B54: **DO NOT create custom variable replacement implementations.** Always use: | C54: ='Ann1 - Step 3'!C54 -> Coding Pattern | D54: ='Ann2 - Step 3'!C54 -> Coding Pattern | E54: =IF(C54=D54, FALSE, TRUE) -> FALSE | G54: =IF(E54=TRUE,F54,D54) -> Coding Pattern
A55: https://github.com/RSSNext/Folo/blob/main/AGENTS.md | B55: - Styling: NativewindCSS; do not use external `StyleSheet.create` for new UI. | C55: ='Ann1 - Step 3'!C55 -> Coding Pattern | D55: ='Ann2 - Step 3'!C55 -> Coding Pattern | E55: =IF(C55=D55, FALSE, TRUE) -> FALSE | G55: =IF(E55=TRUE,F55,D55) -> Coding Pattern
... A58: https://github.com/rustfs/rustfs/blob/main/AGENTS.md | B58: Do not open a PR with code changes when the required checks fail. | C58: ='Ann1 - Step 3'!C58 -> Commit&PR rule | D58: ='Ann2 - Step 3'!C58 -> Commit&PR rule | E58: =IF(C58=D58, FALSE, TRUE) -> FALSE | G58: =IF(E58=TRUE,F58,D58) -> Commit&PR rule
A59: https://github.com/rustfs/rustfs/blob/main/AGENTS.md | B59: - Do not include the literal sequence `\n` in any GitHub issue, pull request, or discussion comment. | C59: ='Ann1 - Step 3'!C59 -> Commit&PR rule | D59: ='Ann2 - Step 3'!C59 -> Writing Style Preference | E59: =IF(C59=D59, FALSE, TRUE) -> TRUE | F59: Commit&PR rule | G59: =IF(E59=TRUE,F59,D59) -> Commit&PR rule
A60: https://github.com/seasonedcc/remix-forms/blob/main/AGENTS.md | B60: - Do not test Zod schemas. | C60: ='Ann1 - Step 3'!C60 -> Testing | D60: ='Ann2 - Step 3'!C60 -> Testing | E60: =IF(C60=D60, FALSE, TRUE) -> FALSE | G60: =IF(E60=TRUE,F60,D60) -> Testing
A61: https://github.com/SimonHalvdansson/Harmonic-HN/blob/main/AGENTS.md | B61: - Do not update the changelog unless the user explicitly asks for it. | C61: ='Ann1 - Step 3'!C61 -> Documentation | D61: ='Ann2 - Step 3'!C61 -> Documentation | E61: =IF(C61=D61, FALSE, TRUE) -> FALSE | G61: =IF(E61=TRUE,F61,D61) -> Documentation
A62: https://github.com/stack-auth/stack-auth/blob/main/AGENTS.md | B62: Do NOT call build:packages, dev, codegen, or anything like that yourself, as the dev is already running it. | C62: ='Ann1 - Step 3'!C62 -> Build & Operation | D62: ='Ann2 - Step 3'!C62 -> Build & Operation | E62: =IF(C62=D62, FALSE, TRUE) -> FALSE | G62: =IF(E62=TRUE,F62,D62) -> Build & Operation
A63: https://github.com/stack-auth/stack-auth/blob/main/AGENTS.md | B63: - Do NOT use `as`/`any`/type casts or anything else like that to bypass the type system unless you specifically asked the user about it. | C63: ='Ann1 - Step 3'!C63 -> Coding Pattern | D63: ='Ann2 - Step 3'!C63 -> Coding Pattern | E63: =IF(C63=D63, FALSE, TRUE) -> FALSE | G63: =IF(E63=TRUE,F63,D63) -> Coding Pattern
A64: https://github.com/swarmauri/swarmauri-sdk/blob/main/AGENTS.md | B64: list Jacob Stewart `<jacob@swarmauri.com>` as an author (do not add the | C64: ='Ann1 - Step 3'!C64 -> Commit&PR rule | D64: ='Ann2 - Step 3'!C64 -> Commit&PR rule | E64: =IF(C64=D64, FALSE, TRUE) -> FALSE | G64: =IF(E64=TRUE,F64,D64) -> Commit&PR rule
A65: https://github.com/theopenco/llmgateway/blob/main/AGENTS.md | B65: Do not run test files or suites in parallel unless the repository instructions for that exact suite explicitly require it. | C65: ='Ann1 - Step 3'!C65 -> Testing | D65: ='Ann2 - Step 3'!C65 -> Testing | E65: =IF(C65=D65, FALSE, TRUE) -> FALSE | G65: =IF(E65=TRUE,F65,D65) -> Testing
A66: https://github.com/theopenco/llmgateway/blob/main/AGENTS.md | B66: Do NOT attempt to manually edit or resolve conflicts in any file under `packages/db/migrations/` | C66: ='Ann1 - Step 3'!C66 -> Commit&PR rule | D66: ='Ann2 - Step 3'!C66 -> Commit&PR rule | E66: =IF(C66=D66, FALSE, TRUE) -> FALSE | G66: =IF(E66=TRUE,F66,D66) -> Commit&PR rule
A67: https://github.com/theopenco/llmgateway/blob/main/AGENTS.md | B67: - Do not use useEffect for data fetching in the UI; instead, use TanStack Query for all data fetching and state management. | C67: ='Ann1 - Step 3'!C67 -> Coding Pattern | D67: ='Ann2 - Step 3'!C67 -> Coding Pattern | E67: =IF(C67=D67, FALSE, TRUE) -> FALSE | G67: =IF(E67=TRUE,F67,D67) -> Coding Pattern
A68: https://github.com/theopenco/llmgateway/blob/main/AGENTS.md | B68: - Do not --amend commits after pushing to remote | C68: ='Ann1 - Step 3'!C68 -> Commit&PR rule | D68: ='Ann2 - Step 3'!C68 -> Commit&PR rule | E68: =IF(C68=D68, FALSE, TRUE) -> FALSE | G68: =IF(E68=TRUE,F68,D68) -> Commit&PR rule
A69: https://github.com/theopenco/llmgateway/blob/main/AGENTS.md | B69: - Do not add explicit caching or memoization around `process.env` reads or parsed env-var values unless there is a measured hot-path need | C69: ='Ann1 - Step 3'!C69 -> Performance | D69: ='Ann2 - Step 3'!C69 -> Performance | E69: =IF(C69=D69, FALSE, TRUE) -> FALSE | G69: =IF(E69=TRUE,F69,D69) -> Performance
A70: https://github.com/theopenco/llmgateway/blob/main/AGENTS.md | B70: - Do not use broad try/catch in API handlers unless to check for specific errors; instead, let errors propagate and be handled by the global error handler | C70: ='Ann1 - Step 3'!C70 -> Coding Pattern | D70: ='Ann2 - Step 3'!C70 -> Coding Pattern | E70: =IF(C70=D70, FALSE, TRUE) -> FALSE | G70: =IF(E70=TRUE,F70,D70) -> Coding Pattern
A71: https://github.com/useautumn/autumn/blob/main/AGENTS.md | B71: For runtime balance/reset/cache patch flows, do not bump `cache_version` in cache writers or Lua update scripts. | C71: ='Ann1 - Step 3'!C71 -> Coding Pattern | D71: ='Ann2 - Step 3'!C71 -> Coding Pattern | E71: =IF(C71=D71, FALSE, TRUE) -> FALSE | G71: =IF(E71=TRUE,F71,D71) -> Coding Pattern
... A74: https://github.com/valkey-io/valkey-glide/blob/main/AGENTS.md | B74: - Do not modify vendored or third-party code | C74: ='Ann1 - Step 3'!C74 -> Task Execution | D74: ='Ann2 - Step 3'!C74 -> Task Execution | E74: =IF(C74=D74, FALSE, TRUE) -> FALSE | G74: =IF(E74=TRUE,F74,D74) -> Task Execution
A75: https://github.com/wandb/weave/blob/master/AGENTS.md | B75: - Do NOT use bare `python -m pytest` — the `python` on PATH may be from a uv cache, not the project `.venv`. | C75: ='Ann1 - Step 3'!C75 -> Testing | D75: ='Ann2 - Step 3'!C75 -> Build & Operation | E75: =IF(C75=D75, FALSE, TRUE) -> TRUE | F75: Testing | G75: =IF(E75=TRUE,F75,D75) -> Testing
A76: https://github.com/wandb/weave/blob/master/AGENTS.md | B76: - Do NOT use `--extra test` — `test` is a dependency-group, not an optional-dependency. | C76: ='Ann1 - Step 3'!C76 -> Build & Operation | D76: ='Ann2 - Step 3'!C76 -> Testing | E76: =IF(C76=D76, FALSE, TRUE) -> TRUE | F76: Testing | G76: =IF(E76=TRUE,F76,D76) -> Testing
A77: https://github.com/web-infra-dev/rspack/blob/main/AGENTS.md | B77: - **Rule of thumb**: Do not use `tokio` to parallelize synchronous CPU-heavy work, and do not introduce `rayon` inside async orchestration that should stay within `rspack_parallel` | C77: ='Ann1 - Step 3'!C77 -> Performance | D77: ='Ann2 - Step 3'!C77 -> Performance | E77: =IF(C77=D77, FALSE, TRUE) -> FALSE | G77: =IF(E77=TRUE,F77,D77) -> Performance
A78: https://github.com/webgptorg/promptbook/blob/main/AGENTS.md | B78: Do not edit these places manually, as they will be overwritten by the code generation process. | C78: ='Ann1 - Step 3'!C78 -> Task Execution | D78: ='Ann2 - Step 3'!C78 -> Task Execution | E78: =IF(C78=D78, FALSE, TRUE) -> FALSE | G78: =IF(E78=TRUE,F78,D78) -> Task Execution
A79: https://github.com/webgptorg/promptbook/blob/main/AGENTS.md | B79: - You (the AI coding agent) are running inside a Node process, so do not kill all Node processes such as `taskkill /F /IM node.exe`. | C79: ='Ann1 - Step 3'!C79 -> Build & Operation | D79: ='Ann2 - Step 3'!C79 -> Task Execution | E79: =IF(C79=D79, FALSE, TRUE) -> TRUE | F79: Task Execution | G79: =IF(E79=TRUE,F79,D79) -> Task Execution
A80: https://github.com/webgptorg/promptbook/blob/main/AGENTS.md | B80: is fine, but do not remove or rename existing ones, and do not change the meaning of existing columns or tables. | C80: ='Ann1 - Step 3'!C80 -> Task Execution | D80: ='Ann2 - Step 3'!C80 -> Task Execution | E80: =IF(C80=D80, FALSE, TRUE) -> FALSE | G80: =IF(E80=TRUE,F80,D80) -> Task Execution
A81: https://github.com/webgptorg/promptbook/blob/main/AGENTS.md | B81: Do not add any additional features or make any additional changes that are not described there. | C81: ='Ann1 - Step 3'!C81 -> Task Execution | D81: ='Ann2 - Step 3'!C81 -> Task Execution | E81: =IF(C81=D81, FALSE, TRUE) -> FALSE | G81: =IF(E81=TRUE,F81,D81) -> Task Execution
A82: https://github.com/wieslawsoltes/Dock/blob/master/AGENTS.md | B82: - Use `ReactiveUI.Avalonia` (latest) and do not use `Avalonia.ReactiveUI` directly. | C82: ='Ann1 - Step 3'!C82 -> Coding Pattern | D82: ='Ann2 - Step 3'!C82 -> Coding Pattern | E82: =IF(C82=D82, FALSE, TRUE) -> FALSE | G82: =IF(E82=TRUE,F82,D82) -> Coding Pattern
A83: https://github.com/wieslawsoltes/Dock/blob/master/AGENTS.md | B83: isolate it to the docking layer and do not reference it from app UI code. | C83: ='Ann1 - Step 3'!C83 -> Coding Pattern | D83: ='Ann2 - Step 3'!C83 -> Coding Pattern | E83: =IF(C83=D83, FALSE, TRUE) -> FALSE | G83: =IF(E83=TRUE,F83,D83) -> Coding Pattern
A84: https://github.com/wieslawsoltes/Dock/blob/master/AGENTS.md | B84: - Do not dispose services resolved from the container manually. | C84: ='Ann1 - Step 3'!C84 -> Coding Pattern | D84: ='Ann2 - Step 3'!C84 -> Coding Pattern | E84: =IF(C84=D84, FALSE, TRUE) -> FALSE | G84: =IF(E84=TRUE,F84,D84) -> Coding Pattern
A85: https://github.com/wieslawsoltes/Xaml.Behaviors/blob/master/AGENTS.md | B85: - Use `ReactiveUI.Avalonia` (latest) and do not use `Avalonia.ReactiveUI` directly. | C85: ='Ann1 - Step 3'!C85 -> Coding Pattern | D85: ='Ann2 - Step 3'!C85 -> Coding Pattern | E85: =IF(C85=D85, FALSE, TRUE) -> FALSE | G85: =IF(E85=TRUE,F85,D85) -> Coding Pattern
A86: https://github.com/wieslawsoltes/Xaml.Behaviors/blob/master/AGENTS.md | B86: isolate it to the docking layer and do not reference it from app UI code. | C86: ='Ann1 - Step 3'!C86 -> Coding Pattern | D86: ='Ann2 - Step 3'!C86 -> Coding Pattern | E86: =IF(C86=D86, FALSE, TRUE) -> FALSE | G86: =IF(E86=TRUE,F86,D86) -> Coding Pattern
A87: https://github.com/wieslawsoltes/Xaml.Behaviors/blob/master/AGENTS.md | B87: - Do not dispose services resolved from the container manually. | C87: ='Ann1 - Step 3'!C87 -> Coding Pattern | D87: ='Ann2 - Step 3'!C87 -> Coding Pattern | E87: =IF(C87=D87, FALSE, TRUE) -> FALSE | G87: =IF(E87=TRUE,F87,D87) -> Coding Pattern
A88: https://github.com/yoshiko-pg/difit/blob/main/AGENTS.md | B88: Built artifacts land in `dist/` after `pnpm build`; do not edit them manually. | C88: ='Ann1 - Step 3'!C88 -> Build & Operation | D88: ='Ann2 - Step 3'!C88 -> Build & Operation | E88: =IF(C88=D88, FALSE, TRUE) -> FALSE | G88: =IF(E88=TRUE,F88,D88) -> Build & Operation
A89: https://github.com/zenml-io/zenml/blob/main/AGENTS.md | B89: - Do not use multi-line banner comments to group classes/functions in a module. | C89: ='Ann1 - Step 3'!C89 -> Coding Style | D89: ='Ann2 - Step 3'!C89 -> Coding Style | E89: =IF(C89=D89, FALSE, TRUE) -> FALSE | G89: =IF(E89=TRUE,F89,D89) -> Coding Style
A90: https://github.com/zenml-io/zenml/blob/main/AGENTS.md | B90: - Do NOT try to run the entire test suite locally - many tests require special environments | C90: ='Ann1 - Step 3'!C90 -> Testing | D90: ='Ann2 - Step 3'!C90 -> Testing | E90: =IF(C90=D90, FALSE, TRUE) -> FALSE | G90: =IF(E90=TRUE,F90,D90) -> Testing
A91: https://github.com/Aiko-IT-Systems/DisCatSharp/blob/main/.github/copilot-instructions.md | B91: - Do not ever use non-file-scoped namespaces. | C91: ='Ann1 - Step 3'!C91 -> Coding Style | D91: ='Ann2 - Step 3'!C91 -> Coding Style | E91: =IF(C91=D91, FALSE, TRUE) -> FALSE | G91: =IF(E91=TRUE,F91,D91) -> Coding Style
... A104: https://github.com/dotnet/aspnetcore/blob/main/.github/copilot-instructions.md | B104: * Do not emit "Act", "Arrange" or "Assert" comments. | C104: ='Ann1 - Step 3'!C104 -> Testing | D104: ='Ann2 - Step 3'!C104 -> Testing | E104: =IF(C104=D104, FALSE, TRUE) -> FALSE | G104: =IF(E104=TRUE,F104,D104) -> Testing
A105: https://github.com/dotnet/core/blob/main/.github/copilot-instructions.md | B105: You do not build applications here; you maintain release documentation and validate content. | C105: ='Ann1 - Step 3'!C105 -> Documentation | D105: ='Ann2 - Step 3'!C105 -> Build & Operation | E105: =IF(C105=D105, FALSE, TRUE) -> TRUE | F105: Documentation | G105: =IF(E105=TRUE,F105,D105) -> Documentation
A106: https://github.com/dotnet/core/blob/main/.github/copilot-instructions.md | B106: Do not attempt to build, run, or test code here. | C106: ='Ann1 - Step 3'!C106 -> Task Execution | D106: ='Ann2 - Step 3'!C106 -> Task Execution | E106: =IF(C106=D106, FALSE, TRUE) -> FALSE | G106: =IF(E106=TRUE,F106,D106) -> Task Execution
A107: https://github.com/dotnet/maui/blob/main/.github/copilot-instructions.md | B107: Do NOT default to manually querying AzDO APIs or rely solely on `gh pr checks` pass/fail counts. | C107: ='Ann1 - Step 3'!C107 -> Commit&PR rule | D107: ='Ann2 - Step 3'!C107 -> Build & Operation | E107: =IF(C107=D107, FALSE, TRUE) -> TRUE | F107: Commit&PR rule | G107: =IF(E107=TRUE,F107,D107) -> Commit&PR rule
A108: https://github.com/dotnet/maui/blob/main/.github/copilot-instructions.md | B108: **Verifying specific tests:** When asked "did test X pass?" or "did the new test run?", query the **actual AzDO test results** — do NOT infer whether a test ran by inspecting code attributes. | C108: ='Ann1 - Step 3'!C108 -> Testing | D108: ='Ann2 - Step 3'!C108 -> Testing | E108: =IF(C108=D108, FALSE, TRUE) -> FALSE | G108: =IF(E108=TRUE,F108,D108) -> Testing
A109: https://github.com/dotnet/maui/blob/main/.github/copilot-instructions.md | B109: **Do NOT upgrade Gradle past 8.x** — the Android SDK's `net.android.init.gradle.kts` is incompatible with Gradle 9.x (`dotnet/android#10738`). | C109: ='Ann1 - Step 3'!C109 -> Build & Operation | D109: ='Ann2 - Step 3'!C109 -> Build & Operation | E109: =IF(C109=D109, FALSE, TRUE) -> FALSE | G109: =IF(E109=TRUE,F109,D109) -> Build & Operation
A110: https://github.com/dotnet/maui/blob/main/.github/copilot-instructions.md | B110: **Do NOT rebase, squash, or force-push** unless explicitly requested by the user. | C110: ='Ann1 - Step 3'!C110 -> Commit&PR rule | D110: ='Ann2 - Step 3'!C110 -> Commit&PR rule | E110: =IF(C110=D110, FALSE, TRUE) -> FALSE | G110: =IF(E110=TRUE,F110,D110) -> Commit&PR rule
A111: https://github.com/dotnet/maui/blob/main/.github/copilot-instructions.md | B111: - **Do NOT use for**: Just running tests manually → Use `sandbox-agent` | C111: ='Ann1 - Step 3'!C111 -> Testing | D111: ='Ann2 - Step 3'!C111 -> Testing | E111: =IF(C111=D111, FALSE, TRUE) -> FALSE | G111: =IF(E111=TRUE,F111,D111) -> Testing
A112: https://github.com/dotnet/maui/blob/main/.github/copilot-instructions.md | B112: - **Do NOT use for**: Code review (use pr agent), writing automated tests (use write-tests-agent) | C112: ='Ann1 - Step 3'!C112 -> Task Execution | D112: ='Ann2 - Step 3'!C112 -> Task Execution | E112: =IF(C112=D112, FALSE, TRUE) -> FALSE | G112: =IF(E112=TRUE,F112,D112) -> Task Execution
A113: https://github.com/dotnet/maui/blob/main/.github/copilot-instructions.md | B113: - **Do NOT use for**: Just running tests manually → Use `sandbox-agent` | C113: ='Ann1 - Step 3'!C113 -> Testing | D113: ='Ann2 - Step 3'!C113 -> Testing | E113: =IF(C113=D113, FALSE, TRUE) -> FALSE | G113: =IF(E113=TRUE,F113,D113) -> Testing
A114: https://github.com/dotnet/maui/blob/main/.github/copilot-instructions.md | B114: Do not ask for permission or explain alternatives unless the request is ambiguous. | C114: ='Ann1 - Step 3'!C114 -> Task Execution | D114: ='Ann2 - Step 3'!C114 -> Task Execution | E114: =IF(C114=D114, FALSE, TRUE) -> FALSE | G114: =IF(E114=TRUE,F114,D114) -> Task Execution
A115: https://github.com/dotnet/runtime/blob/main/.github/copilot-instructions.md | B115: Do not simply assume that your changes fix test failures you see, actually build and run those tests again to confirm. | C115: ='Ann1 - Step 3'!C115 -> Testing | D115: ='Ann2 - Step 3'!C115 -> Testing | E115: =IF(C115=D115, FALSE, TRUE) -> FALSE | G115: =IF(E115=TRUE,F115,D115) -> Testing
A116: https://github.com/dotnet/runtime/blob/main/.github/copilot-instructions.md | B116: - When writing tests, do not emit "Act", "Arrange" or "Assert" comments. | C116: ='Ann1 - Step 3'!C116 -> Testing | D116: ='Ann2 - Step 3'!C116 -> Testing | E116: =IF(C116=D116, FALSE, TRUE) -> FALSE | G116: =IF(E116=TRUE,F116,D116) -> Testing
A117: https://github.com/dotnet/runtime/blob/main/.github/copilot-instructions.md | B117: Do not mark a regression test task as complete until both conditions are confirmed. | C117: ='Ann1 - Step 3'!C117 -> Testing | D117: ='Ann2 - Step 3'!C117 -> Testing | E117: =IF(C117=D117, FALSE, TRUE) -> FALSE | G117: =IF(E117=TRUE,F117,D117) -> Testing
A118: https://github.com/dotnet/sdk/blob/main/.github/copilot-instructions.md | B118: Do not run `dotnet format` or make formatting changes to additional files. | C118: ='Ann1 - Step 3'!C118 -> Coding Style | D118: ='Ann2 - Step 3'!C118 -> Build & Operation | E118: =IF(C118=D118, FALSE, TRUE) -> TRUE | F118: Coding Pattern | G118: =IF(E118=TRUE,F118,D118) -> Coding Pattern
A119: https://github.com/esphome/esphome/blob/main/.github/copilot-instructions.md | B119: Do not hardcode secrets or keys. | C119: ='Ann1 - Step 3'!C119 -> Security | D119: ='Ann2 - Step 3'!C119 -> Security | E119: =IF(C119=D119, FALSE, TRUE) -> FALSE | G119: =IF(E119=TRUE,F119,D119) -> Security
A120: https://github.com/friendsofhyperf/components/blob/main/.github/copilot-instructions.md | B120: However, if some tool calls depend on previous calls to inform dependent values like the parameters, do NOT call these tools in parallel and instead call them sequentially. | C120: ='Ann1 - Step 3'!C120 -> Task Execution | D120: ='Ann2 - Step 3'!C120 -> Task Execution | E120: =IF(C120=D120, FALSE, TRUE) -> FALSE | G120: =IF(E120=TRUE,F120,D120) -> Task Execution
A121: https://github.com/geneontology/go-ontology/blob/master/.github/copilot-instructions.md | B121: - IMPORTANT: Do not edit the edit file directly, it's large | C121: ='Ann1 - Step 3'!C121 -> Task Execution | D121: ='Ann2 - Step 3'!C121 -> Task Execution | E121: =IF(C121=D121, FALSE, TRUE) -> FALSE | G121: =IF(E121=TRUE,F121,D121) -> Task Execution
A122: https://github.com/HotCakeX/Harden-Windows-Security/blob/main/.github/copilot-instructions.md | B122: Do not make unnecessary changes to the code. | C122: ='Ann1 - Step 3'!C122 -> Task Execution | D122: ='Ann2 - Step 3'!C122 -> Task Execution | E122: =IF(C122=D122, FALSE, TRUE) -> FALSE | G122: =IF(E122=TRUE,F122,D122) -> Task Execution
A123: https://github.com/HotCakeX/Harden-Windows-Security/blob/main/.github/copilot-instructions.md | B123: Do not use reflection when working with C# or .NET code. | C123: ='Ann1 - Step 3'!C123 -> Coding Pattern | D123: ='Ann2 - Step 3'!C123 -> Coding Pattern | E123: =IF(C123=D123, FALSE, TRUE) -> FALSE | G123: =IF(E123=TRUE,F123,D123) -> Coding Pattern
A124: https://github.com/humanwhocodes/crosspost/blob/main/.github/copilot-instructions.md | B124: - Do not change the working directory when running tests | C124: ='Ann1 - Step 3'!C124 -> Testing | D124: ='Ann2 - Step 3'!C124 -> Testing | E124: =IF(C124=D124, FALSE, TRUE) -> FALSE | G124: =IF(E124=TRUE,F124,D124) -> Testing
A125: https://github.com/igraph/igraph/blob/main/.github/copilot-instructions.md | B125: Do not suggest using these. | C125: ='Ann1 - Step 3'!C125 -> Testing | D125: ='Ann2 - Step 3'!C125 -> Testing | E125: =IF(C125=D125, FALSE, TRUE) -> FALSE | G125: =IF(E125=TRUE,F125,D125) -> Testing
A126: https://github.com/igraph/igraph/blob/main/.github/copilot-instructions.md | B126: If `CHANGELOG.md` was not updated, do not suggest doing so. | C126: ='Ann1 - Step 3'!C126 -> Documentation | D126: ='Ann2 - Step 3'!C126 -> Documentation | E126: =IF(C126=D126, FALSE, TRUE) -> FALSE | G126: =IF(E126=TRUE,F126,D126) -> Documentation
A127: https://github.com/microsoft/ApplicationInsights-JS/blob/main/.github/copilot-instructions.md | B127: - Do not use the spread `...` operator | C127: ='Ann1 - Step 3'!C127 -> Performance | D127: ='Ann2 - Step 3'!C127 -> Performance | E127: =IF(C127=D127, FALSE, TRUE) -> FALSE | G127: =IF(E127=TRUE,F127,D127) -> Performance
A128: https://github.com/microsoft/ApplicationInsights-JS/blob/main/.github/copilot-instructions.md | B128: - Do not use optional chaining `?.` operator | C128: ='Ann1 - Step 3'!C128 -> Performance | D128: ='Ann2 - Step 3'!C128 -> Performance | E128: =IF(C128=D128, FALSE, TRUE) -> FALSE | G128: =IF(E128=TRUE,F128,D128) -> Performance
A129: https://github.com/microsoft/ApplicationInsights-JS/blob/main/.github/copilot-instructions.md | B129: - Do not use the nullish coalescing `??` operator - use `||` instead | C129: ='Ann1 - Step 3'!C129 -> Performance | D129: ='Ann2 - Step 3'!C129 -> Performance | E129: =IF(C129=D129, FALSE, TRUE) -> FALSE | G129: =IF(E129=TRUE,F129,D129) -> Performance
A130: https://github.com/microsoft/ApplicationInsights-JS/blob/main/.github/copilot-instructions.md | B130: - **Async Tests**: Return `IPromise` from test functions for asynchronous operations (do not use deprecated `testCaseAsync`) | C130: ='Ann1 - Step 3'!C130 -> Testing | D130: ='Ann2 - Step 3'!C130 -> Testing | E130: =IF(C130=D130, FALSE, TRUE) -> FALSE | G130: =IF(E130=TRUE,F130,D130) -> Testing
... A135: https://github.com/microsoft/typespec/blob/main/.github/copilot-instructions.md | B135: Those packages are excluded from the pnpm workspace and do not require using pnpm. | C135: ='Ann1 - Step 3'!C135 -> Build & Operation | D135: ='Ann2 - Step 3'!C135 -> Build & Operation | E135: =IF(C135=D135, FALSE, TRUE) -> FALSE | G135: =IF(E135=TRUE,F135,D135) -> Build & Operation
A136: https://github.com/microsoft/typespec/blob/main/.github/copilot-instructions.md | B136: Do NOT bundle different change types into a single entry. | C136: ='Ann1 - Step 3'!C136 -> Documentation | D136: ='Ann2 - Step 3'!C136 -> Commit&PR rule | E136: =IF(C136=D136, FALSE, TRUE) -> TRUE | F136: Commit&PR rule | G136: =IF(E136=TRUE,F136,D136) -> Commit&PR rule
A137: https://github.com/NG-ZORRO/ng-zorro-antd/blob/master/.github/copilot-instructions.md | B137: - Do NOT use the `@HostBinding` and `@HostListener` decorators. | C137: ='Ann1 - Step 3'!C137 -> Coding Pattern | D137: ='Ann2 - Step 3'!C137 -> Coding Pattern | E137: =IF(C137=D137, FALSE, TRUE) -> FALSE | G137: =IF(E137=TRUE,F137,D137) -> Coding Pattern
A138: https://github.com/NG-ZORRO/ng-zorro-antd/blob/master/.github/copilot-instructions.md | B138: - Do NOT use `ngClass`, use `class` bindings instead | C138: ='Ann1 - Step 3'!C138 -> Coding Pattern | D138: ='Ann2 - Step 3'!C138 -> Coding Pattern | E138: =IF(C138=D138, FALSE, TRUE) -> FALSE | G138: =IF(E138=TRUE,F138,D138) -> Coding Pattern
A139: https://github.com/NG-ZORRO/ng-zorro-antd/blob/master/.github/copilot-instructions.md | B139: - Do NOT use `ngStyle`, use `style` bindings instead | C139: ='Ann1 - Step 3'!C139 -> Coding Pattern | D139: ='Ann2 - Step 3'!C139 -> Coding Pattern | E139: =IF(C139=D139, FALSE, TRUE) -> FALSE | G139: =IF(E139=TRUE,F139,D139) -> Coding Pattern
A140: https://github.com/NG-ZORRO/ng-zorro-antd/blob/master/.github/copilot-instructions.md | B140: - Do NOT use `mutate` on signals, use `update` or `set` instead | C140: ='Ann1 - Step 3'!C140 -> Coding Pattern | D140: ='Ann2 - Step 3'!C140 -> Coding Pattern | E140: =IF(C140=D140, FALSE, TRUE) -> FALSE | G140: =IF(E140=TRUE,F140,D140) -> Coding Pattern
A141: https://github.com/NG-ZORRO/ng-zorro-antd/blob/master/.github/copilot-instructions.md | B141: - Do not assume globals like (`new Date()`) are available. | C141: ='Ann1 - Step 3'!C141 -> Coding Pattern | D141: ='Ann2 - Step 3'!C141 -> Coding Pattern | E141: =IF(C141=D141, FALSE, TRUE) -> FALSE | G141: =IF(E141=TRUE,F141,D141) -> Coding Pattern
A142: https://github.com/NG-ZORRO/ng-zorro-antd/blob/master/.github/copilot-instructions.md | B142: - Do not write arrow functions in templates (they are not supported). | C142: ='Ann1 - Step 3'!C142 -> Coding Pattern | D142: ='Ann2 - Step 3'!C142 -> Coding Pattern | E142: =IF(C142=D142, FALSE, TRUE) -> FALSE | G142: =IF(E142=TRUE,F142,D142) -> Coding Pattern
A143: https://github.com/obophenotype/uberon/blob/master/.github/copilot-instructions.md | B143: - DO NOT bother doing your own greps over the file, or looking for other files, unless otherwise asked, you will just waste time. | C143: ='Ann1 - Step 3'!C143 -> Task Execution | D143: ='Ann2 - Step 3'!C143 -> Task Execution | E143: =IF(C143=D143, FALSE, TRUE) -> FALSE | G143: =IF(E143=TRUE,F143,D143) -> Task Execution
A144: https://github.com/obophenotype/uberon/blob/master/.github/copilot-instructions.md | B144: - IMPORTANT: Do not edit the edit file directly, it's large | C144: ='Ann1 - Step 3'!C144 -> Task Execution | D144: ='Ann2 - Step 3'!C144 -> Task Execution | E144: =IF(C144=D144, FALSE, TRUE) -> FALSE | G144: =IF(E144=TRUE,F144,D144) -> Task Execution
...

Sheet Step 3 Stats
A1: Ann1 | B1: Ann2 | D1: N | E1: =COUNTA(A2:A2462) -> 1942
A2: =IFERROR(__xludf.DUMMYFUNCTION("FILTER( {TO_TEXT(IFERROR('Step3 Merge'!C2:C2462,"""")),TO_TEXT(IFERROR('Step3 Merge'!D2:D2462,""""))}, LEN(TRIM(TO_TEXT(IFERROR('Step3 Merge'!C2:C2462,""""))))>0, LEN(TRIM(TO_TEXT(IFERROR('Step3 Merge'!D2:D2462,""""))))>0, TO_TEXT(IFERROR('Step3 M"&"erge'!C2:C2462,""""))<>""#REF!"", TO_TEXT(IFERROR('Step3 Merge'!D2:D2462,""""))<>""#REF!"" )"),"Documentation") -> Documentation | B2: =IFERROR(__xludf.DUMMYFUNCTION("""COMPUTED_VALUE"""),"Documentation") -> Documentation | D2: Observed agreement | E2: =SUMPRODUCT((A2:A2462<>"")*(A2:A2462=B2:B2462))/E1 -> 0.85736354 | G2: =IFERROR(__xludf.DUMMYFUNCTION("SORT(UNIQUE(FILTER({A2:A2462;B2:B2462},{A2:A2462;B2:B2462}<>"""")))"),"Build & Operation") -> Build & Operation | H2: {=IF(G2:G2462="",,COUNTIF($A$2:$A2462,G2:G2462)/$E$1)} -> 0.11277034 | I2: {=IF(G2:G2462="",,COUNTIF($B$2:$B2462,G2:G2462)/$E$1)} -> 0.11791967 | J2: {=IF(G2:G2462="",,H2:H2462*I2:I2462)} -> 0.013297841
A3: =IFERROR(__xludf.DUMMYFUNCTION("""COMPUTED_VALUE"""),"Coding Pattern") -> Coding Pattern | B3: =IFERROR(__xludf.DUMMYFUNCTION("""COMPUTED_VALUE"""),"Coding Pattern") -> Coding Pattern | D3: Expected agreement | E3: =SUM(J2:J2462) -> 0.14541715 | G3: =IFERROR(__xludf.DUMMYFUNCTION("""COMPUTED_VALUE"""),"Code Review") -> Code Review | H3: 0.0056642636 | I3: 0.0061791967 | J3: 3.5000599e-05
A4: =IFERROR(__xludf.DUMMYFUNCTION("""COMPUTED_VALUE"""),"Testing") -> Testing | B4: =IFERROR(__xludf.DUMMYFUNCTION("""COMPUTED_VALUE"""),"Testing") -> Testing | D4: Cohen’s κ | E4: =IF(1-E3=0,"Kappa undefined",(E2-E3)/(1-E3)) -> 0.8330923 | G4: =IFERROR(__xludf.DUMMYFUNCTION("""COMPUTED_VALUE"""),"Coding Pattern") -> Coding Pattern | H4: 0.26570546 | I4: 0.27394439 | J4: 0.072788519
A5: =IFERROR(__xludf.DUMMYFUNCTION("""COMPUTED_VALUE"""),"Documentation") -> Documentation | B5: =IFERROR(__xludf.DUMMYFUNCTION("""COMPUTED_VALUE"""),"Documentation") -> Documentation | G5: =IFERROR(__xludf.DUMMYFUNCTION("""COMPUTED_VALUE"""),"Coding Style") -> Coding Style | H5: 0.078784758 | I5: 0.077754892 | J5: 0.0061259003
A6: =IFERROR(__xludf.DUMMYFUNCTION("""COMPUTED_VALUE"""),"Documentation") -> Documentation | B6: =IFERROR(__xludf.DUMMYFUNCTION("""COMPUTED_VALUE"""),"Documentation") -> Documentation | G6: =IFERROR(__xludf.DUMMYFUNCTION("""COMPUTED_VALUE"""),"Commit&PR rule") -> Commit&PR rule | H6: 0.076210093 | I6: 0.076210093 | J6: 0.0058079782
A7: =IFERROR(__xludf.DUMMYFUNCTION("""COMPUTED_VALUE"""),"Documentation") -> Documentation | B7: =IFERROR(__xludf.DUMMYFUNCTION("""COMPUTED_VALUE"""),"Documentation") -> Documentation | G7: =IFERROR(__xludf.DUMMYFUNCTION("""COMPUTED_VALUE"""),"Documentation") -> Documentation | H7: 0.058187436 | I7: 0.061791967 | J7: 0.0035955161
A8: =IFERROR(__xludf.DUMMYFUNCTION("""COMPUTED_VALUE"""),"Documentation") -> Documentation | B8: =IFERROR(__xludf.DUMMYFUNCTION("""COMPUTED_VALUE"""),"Documentation") -> Documentation | G8: =IFERROR(__xludf.DUMMYFUNCTION("""COMPUTED_VALUE"""),"Maintainability") -> Maintainability | H8: 0.020597322 | I8: 0.01853759 | J8: 0.00038182472
A9: =IFERROR(__xludf.DUMMYFUNCTION("""COMPUTED_VALUE"""),"Task Execution") -> Task Execution | B9: =IFERROR(__xludf.DUMMYFUNCTION("""COMPUTED_VALUE"""),"Task Execution") -> Task Execution | G9: =IFERROR(__xludf.DUMMYFUNCTION("""COMPUTED_VALUE"""),"NOT_ENOUGH_CONTEXT") -> NOT_ENOUGH_CONTEXT | H9: 0.01853759 | I9: 0.0092687951 | J9: 0.00017182112
A10: =IFERROR(__xludf.DUMMYFUNCTION("""COMPUTED_VALUE"""),"Commit&PR rule") -> Commit&PR rule | B10: =IFERROR(__xludf.DUMMYFUNCTION("""COMPUTED_VALUE"""),"Commit&PR rule") -> Commit&PR rule | G10: =IFERROR(__xludf.DUMMYFUNCTION("""COMPUTED_VALUE"""),"Other") -> Other | H10: 0 | I10: 0.0020597322 | J10: 0
A11: =IFERROR(__xludf.DUMMYFUNCTION("""COMPUTED_VALUE"""),"Coding Pattern") -> Coding Pattern | B11: =IFERROR(__xludf.DUMMYFUNCTION("""COMPUTED_VALUE"""),"Coding Pattern") -> Coding Pattern | G11: =IFERROR(__xludf.DUMMYFUNCTION("""COMPUTED_VALUE"""),"Performance") -> Performance | H11: 0.012873326 | I11: 0.013903193 | J11: 0.00017898034
A12: =IFERROR(__xludf.DUMMYFUNCTION("""COMPUTED_VALUE"""),"Coding Pattern") -> Coding Pattern | B12: =IFERROR(__xludf.DUMMYFUNCTION("""COMPUTED_VALUE"""),"Coding Pattern") -> Coding Pattern | G12: =IFERROR(__xludf.DUMMYFUNCTION("""COMPUTED_VALUE"""),"Security") -> Security | H12: 0.038105046 | I12: 0.03707518 | J12: 0.0014127515
A13: =IFERROR(__xludf.DUMMYFUNCTION("""COMPUTED_VALUE"""),"Documentation") -> Documentation | B13: =IFERROR(__xludf.DUMMYFUNCTION("""COMPUTED_VALUE"""),"Documentation") -> Documentation | G13: =IFERROR(__xludf.DUMMYFUNCTION("""COMPUTED_VALUE"""),"Task Execution") -> Task Execution | H13: 0.17353244 | I13: 0.17095778 | J13: 0.02966672
A14: =IFERROR(__xludf.DUMMYFUNCTION("""COMPUTED_VALUE"""),"Coding Pattern") -> Coding Pattern | B14: =IFERROR(__xludf.DUMMYFUNCTION("""COMPUTED_VALUE"""),"Coding Pattern") -> Coding Pattern | G14: =IFERROR(__xludf.DUMMYFUNCTION("""COMPUTED_VALUE"""),"Testing") -> Testing | H14: 0.10401648 | I14: 0.10504634 | J14: 0.010926551
A15: =IFERROR(__xludf.DUMMYFUNCTION("""COMPUTED_VALUE"""),"Coding Pattern") -> Coding Pattern | B15: =IFERROR(__xludf.DUMMYFUNCTION("""COMPUTED_VALUE"""),"Coding Pattern") -> Coding Pattern | G15: =IFERROR(__xludf.DUMMYFUNCTION("""COMPUTED_VALUE"""),"Writing Style Preference") -> Writing Style Preference | H15: 0.035015448 | I15: 0.029351184 | J15: 0.0010277449
A16: =IFERROR(__xludf.DUMMYFUNCTION("""COMPUTED_VALUE"""),"Coding Pattern") -> Coding Pattern | B16: =IFERROR(__xludf.DUMMYFUNCTION("""COMPUTED_VALUE"""),"Coding Pattern") -> Coding Pattern | H16: 0 | I16: 0 | J16: 0
A17: =IFERROR(__xludf.DUMMYFUNCTION("""COMPUTED_VALUE"""),"Coding Pattern") -> Coding Pattern | B17: =IFERROR(__xludf.DUMMYFUNCTION("""COMPUTED_VALUE"""),"Coding Pattern") -> Coding Pattern | H17: 0 | I17: 0 | J17: 0
A18: =IFERROR(__xludf.DUMMYFUNCTION("""COMPUTED_VALUE"""),"Coding Pattern") -> Coding Pattern | B18: =IFERROR(__xludf.DUMMYFUNCTION("""COMPUTED_VALUE"""),"Coding Pattern") -> Coding Pattern | H18: 0 | I18: 0 | J18: 0
A19: =IFERROR(__xludf.DUMMYFUNCTION("""COMPUTED_VALUE"""),"Coding Pattern") -> Coding Pattern | B19: =IFERROR(__xludf.DUMMYFUNCTION("""COMPUTED_VALUE"""),"Coding Pattern") -> Coding Pattern | H19: 0 | I19: 0 | J19: 0
A20: =IFERROR(__xludf.DUMMYFUNCTION("""COMPUTED_VALUE"""),"Coding Pattern") -> Coding Pattern | B20: =IFERROR(__xludf.DUMMYFUNCTION("""COMPUTED_VALUE"""),"Coding Pattern") -> Coding Pattern | H20: 0 | I20: 0 | J20: 0
A21: =IFERROR(__xludf.DUMMYFUNCTION("""COMPUTED_VALUE"""),"Testing") -> Testing | B21: =IFERROR(__xludf.DUMMYFUNCTION("""COMPUTED_VALUE"""),"Testing") -> Testing | H21: 0 | I21: 0 | J21: 0
A22: =IFERROR(__xludf.DUMMYFUNCTION("""COMPUTED_VALUE"""),"Build & Operation") -> Build & Operation | B22: =IFERROR(__xludf.DUMMYFUNCTION("""COMPUTED_VALUE"""),"Build & Operation") -> Build & Operation | H22: 0 | I22: 0 | J22: 0
A23: =IFERROR(__xludf.DUMMYFUNCTION("""COMPUTED_VALUE"""),"Coding Pattern") -> Coding Pattern | B23: =IFERROR(__xludf.DUMMYFUNCTION("""COMPUTED_VALUE"""),"Coding Pattern") -> Coding Pattern | H23: 0 | I23: 0 | J23: 0
A24: =IFERROR(__xludf.DUMMYFUNCTION("""COMPUTED_VALUE"""),"Coding Pattern") -> Coding Pattern | B24: =IFERROR(__xludf.DUMMYFUNCTION("""COMPUTED_VALUE"""),"Coding Pattern") -> Coding Pattern | H24: 0 | I24: 0 | J24: 0
A25: =IFERROR(__xludf.DUMMYFUNCTION("""COMPUTED_VALUE"""),"Coding Pattern") -> Coding Pattern | B25: =IFERROR(__xludf.DUMMYFUNCTION("""COMPUTED_VALUE"""),"Coding Pattern") -> Coding Pattern | H25: 0 | I25: 0 | J25: 0
A26: =IFERROR(__xludf.DUMMYFUNCTION("""COMPUTED_VALUE"""),"Task Execution") -> Task Execution | B26: =IFERROR(__xludf.DUMMYFUNCTION("""COMPUTED_VALUE"""),"Task Execution") -> Task Execution | H26: 0 | I26: 0 | J26: 0
A27: =IFERROR(__xludf.DUMMYFUNCTION("""COMPUTED_VALUE"""),"Task Execution") -> Task Execution | B27: =IFERROR(__xludf.DUMMYFUNCTION("""COMPUTED_VALUE"""),"Task Execution") -> Task Execution | H27: 0 | I27: 0 | J27: 0
A28: =IFERROR(__xludf.DUMMYFUNCTION("""COMPUTED_VALUE"""),"Coding Pattern") -> Coding Pattern | B28: =IFERROR(__xludf.DUMMYFUNCTION("""COMPUTED_VALUE"""),"Coding Pattern") -> Coding Pattern | H28: 0 | I28: 0 | J28: 0
A29: =IFERROR(__xludf.DUMMYFUNCTION("""COMPUTED_VALUE"""),"Coding Pattern") -> Coding Pattern | B29: =IFERROR(__xludf.DUMMYFUNCTION("""COMPUTED_VALUE"""),"Coding Pattern") -> Coding Pattern | H29: 0 | I29: 0 | J29: 0
A30: =IFERROR(__xludf.DUMMYFUNCTION("""COMPUTED_VALUE"""),"Coding Pattern") -> Coding Pattern | B30: =IFERROR(__xludf.DUMMYFUNCTION("""COMPUTED_VALUE"""),"Coding Pattern") -> Coding Pattern | H30: 0 | I30: 0 | J30: 0
A31: =IFERROR(__xludf.DUMMYFUNCTION("""COMPUTED_VALUE"""),"Coding Pattern") -> Coding Pattern | B31: =IFERROR(__xludf.DUMMYFUNCTION("""COMPUTED_VALUE"""),"Coding Pattern") -> Coding Pattern | H31: 0 | I31: 0 | J31: 0
A32: =IFERROR(__xludf.DUMMYFUNCTION("""COMPUTED_VALUE"""),"Coding Pattern") -> Coding Pattern | B32: =IFERROR(__xludf.DUMMYFUNCTION("""COMPUTED_VALUE"""),"Coding Pattern") -> Coding Pattern | H32: 0 | I32: 0 | J32: 0
A33: =IFERROR(__xludf.DUMMYFUNCTION("""COMPUTED_VALUE"""),"Coding Pattern") -> Coding Pattern | B33: =IFERROR(__xludf.DUMMYFUNCTION("""COMPUTED_VALUE"""),"Coding Pattern") -> Coding Pattern | H33: 0 | I33: 0 | J33: 0
A34: =IFERROR(__xludf.DUMMYFUNCTION("""COMPUTED_VALUE"""),"Coding Style") -> Coding Style | B34: =IFERROR(__xludf.DUMMYFUNCTION("""COMPUTED_VALUE"""),"Coding Style") -> Coding Style | H34: 0 | I34: 0 | J34: 0
A35: =IFERROR(__xludf.DUMMYFUNCTION("""COMPUTED_VALUE"""),"Build & Operation") -> Build & Operation | B35: =IFERROR(__xludf.DUMMYFUNCTION("""COMPUTED_VALUE"""),"Build & Operation") -> Build & Operation | H35: 0 | I35: 0 | J35: 0
A36: =IFERROR(__xludf.DUMMYFUNCTION("""COMPUTED_VALUE"""),"Task Execution") -> Task Execution | B36: =IFERROR(__xludf.DUMMYFUNCTION("""COMPUTED_VALUE"""),"Task Execution") -> Task Execution | H36: 0 | I36: 0 | J36: 0
A37: =IFERROR(__xludf.DUMMYFUNCTION("""COMPUTED_VALUE"""),"Coding Style") -> Coding Style | B37: =IFERROR(__xludf.DUMMYFUNCTION("""COMPUTED_VALUE"""),"Coding Style") -> Coding Style | H37: 0 | I37: 0 | J37: 0
A38: =IFERROR(__xludf.DUMMYFUNCTION("""COMPUTED_VALUE"""),"Documentation") -> Documentation | B38: =IFERROR(__xludf.DUMMYFUNCTION("""COMPUTED_VALUE"""),"Documentation") -> Documentation | H38: 0 | I38: 0 | J38: 0
A39: =IFERROR(__xludf.DUMMYFUNCTION("""COMPUTED_VALUE"""),"Documentation") -> Documentation | B39: =IFERROR(__xludf.DUMMYFUNCTION("""COMPUTED_VALUE"""),"Task Execution") -> Task Execution | H39: 0 | I39: 0 | J39: 0
A40: =IFERROR(__xludf.DUMMYFUNCTION("""COMPUTED_VALUE"""),"Coding Pattern") -> Coding Pattern | B40: =IFERROR(__xludf.DUMMYFUNCTION("""COMPUTED_VALUE"""),"Coding Pattern") -> Coding Pattern | H40: 0 | I40: 0 | J40: 0
A41: =IFERROR(__xludf.DUMMYFUNCTION("""COMPUTED_VALUE"""),"Commit&PR rule") -> Commit&PR rule | B41: =IFERROR(__xludf.DUMMYFUNCTION("""COMPUTED_VALUE"""),"Commit&PR rule") -> Commit&PR rule | H41: 0 | I41: 0 | J41: 0
A42: =IFERROR(__xludf.DUMMYFUNCTION("""COMPUTED_VALUE"""),"Build & Operation") -> Build & Operation | B42: =IFERROR(__xludf.DUMMYFUNCTION("""COMPUTED_VALUE"""),"Build & Operation") -> Build & Operation | H42: 0 | I42: 0 | J42: 0
A43: =IFERROR(__xludf.DUMMYFUNCTION("""COMPUTED_VALUE"""),"Task Execution") -> Task Execution | B43: =IFERROR(__xludf.DUMMYFUNCTION("""COMPUTED_VALUE"""),"Build & Operation") -> Build & Operation | H43: 0 | I43: 0 | J43: 0
A44: =IFERROR(__xludf.DUMMYFUNCTION("""COMPUTED_VALUE"""),"Coding Style") -> Coding Style | B44: =IFERROR(__xludf.DUMMYFUNCTION("""COMPUTED_VALUE"""),"Coding Style") -> Coding Style | H44: 0 | I44: 0 | J44: 0
A45: =IFERROR(__xludf.DUMMYFUNCTION("""COMPUTED_VALUE"""),"Task Execution") -> Task Execution | B45: =IFERROR(__xludf.DUMMYFUNCTION("""COMPUTED_VALUE"""),"Task Execution") -> Task Execution | H45: 0 | I45: 0 | J45: 0
A46: =IFERROR(__xludf.DUMMYFUNCTION("""COMPUTED_VALUE"""),"Task Execution") -> Task Execution | B46: =IFERROR(__xludf.DUMMYFUNCTION("""COMPUTED_VALUE"""),"Task Execution") -> Task Execution | H46: 0 | I46: 0 | J46: 0
A47: =IFERROR(__xludf.DUMMYFUNCTION("""COMPUTED_VALUE"""),"Task Execution") -> Task Execution | B47: =IFERROR(__xludf.DUMMYFUNCTION("""COMPUTED_VALUE"""),"Task Execution") -> Task Execution | H47: 0 | I47: 0 | J47: 0
A48: =IFERROR(__xludf.DUMMYFUNCTION("""COMPUTED_VALUE"""),"Task Execution") -> Task Execution | B48: =IFERROR(__xludf.DUMMYFUNCTION("""COMPUTED_VALUE"""),"Task Execution") -> Task Execution | H48: 0 | I48: 0 | J48: 0
A49: =IFERROR(__xludf.DUMMYFUNCTION("""COMPUTED_VALUE"""),"Coding Pattern") -> Coding Pattern | B49: =IFERROR(__xludf.DUMMYFUNCTION("""COMPUTED_VALUE"""),"Coding Pattern") -> Coding Pattern | H49: 0 | I49: 0 | J49: 0
A50: =IFERROR(__xludf.DUMMYFUNCTION("""COMPUTED_VALUE"""),"Task Execution") -> Task Execution | B50: =IFERROR(__xludf.DUMMYFUNCTION("""COMPUTED_VALUE"""),"Task Execution") -> Task Execution | H50: 0 | I50: 0 | J50: 0
A51: =IFERROR(__xludf.DUMMYFUNCTION("""COMPUTED_VALUE"""),"Task Execution") -> Task Execution | B51: =IFERROR(__xludf.DUMMYFUNCTION("""COMPUTED_VALUE"""),"Task Execution") -> Task Execution | H51: 0 | I51: 0 | J51: 0
A52: =IFERROR(__xludf.DUMMYFUNCTION("""COMPUTED_VALUE"""),"Task Execution") -> Task Execution | B52: =IFERROR(__xludf.DUMMYFUNCTION("""COMPUTED_VALUE"""),"Task Execution") -> Task Execution | H52: 0 | I52: 0 | J52: 0
A53: =IFERROR(__xludf.DUMMYFUNCTION("""COMPUTED_VALUE"""),"Maintainability") -> Maintainability | B53: =IFERROR(__xludf.DUMMYFUNCTION("""COMPUTED_VALUE"""),"Maintainability") -> Maintainability | H53: 0 | I53: 0 | J53: 0
A54: =IFERROR(__xludf.DUMMYFUNCTION("""COMPUTED_VALUE"""),"Coding Pattern") -> Coding Pattern | B54: =IFERROR(__xludf.DUMMYFUNCTION("""COMPUTED_VALUE"""),"Coding Pattern") -> Coding Pattern | H54: 0 | I54: 0 | J54: 0
A55: =IFERROR(__xludf.DUMMYFUNCTION("""COMPUTED_VALUE"""),"Coding Pattern") -> Coding Pattern | B55: =IFERROR(__xludf.DUMMYFUNCTION("""COMPUTED_VALUE"""),"Coding Pattern") -> Coding Pattern | H55: 0 | I55: 0 | J55: 0
A56: =IFERROR(__xludf.DUMMYFUNCTION("""COMPUTED_VALUE"""),"Coding Pattern") -> Coding Pattern | B56: =IFERROR(__xludf.DUMMYFUNCTION("""COMPUTED_VALUE"""),"Coding Pattern") -> Coding Pattern | H56: 0 | I56: 0 | J56: 0
A57: =IFERROR(__xludf.DUMMYFUNCTION("""COMPUTED_VALUE"""),"Task Execution") -> Task Execution | B57: =IFERROR(__xludf.DUMMYFUNCTION("""COMPUTED_VALUE"""),"Task Execution") -> Task Execution | H57: 0 | I57: 0 | J57: 0
A58: =IFERROR(__xludf.DUMMYFUNCTION("""COMPUTED_VALUE"""),"Commit&PR rule") -> Commit&PR rule | B58: =IFERROR(__xludf.DUMMYFUNCTION("""COMPUTED_VALUE"""),"Commit&PR rule") -> Commit&PR rule | H58: 0 | I58: 0 | J58: 0
A59: =IFERROR(__xludf.DUMMYFUNCTION("""COMPUTED_VALUE"""),"Commit&PR rule") -> Commit&PR rule | B59: =IFERROR(__xludf.DUMMYFUNCTION("""COMPUTED_VALUE"""),"Writing Style Preference") -> Writing Style Preference | H59: 0 | I59: 0 | J59: 0
A60: =IFERROR(__xludf.DUMMYFUNCTION("""COMPUTED_VALUE"""),"Testing") -> Testing | B60: =IFERROR(__xludf.DUMMYFUNCTION("""COMPUTED_VALUE"""),"Testing") -> Testing | H60: 0 | I60: 0 | J60: 0
A61: =IFERROR(__xludf.DUMMYFUNCTION("""COMPUTED_VALUE"""),"Documentation") -> Documentation | B61: =IFERROR(__xludf.DUMMYFUNCTION("""COMPUTED_VALUE"""),"Documentation") -> Documentation | H61: 0 | I61: 0 | J61: 0
A62: =IFERROR(__xludf.DUMMYFUNCTION("""COMPUTED_VALUE"""),"Build & Operation") -> Build & Operation | B62: =IFERROR(__xludf.DUMMYFUNCTION("""COMPUTED_VALUE"""),"Build & Operation") -> Build & Operation | H62: 0 | I62: 0 | J62: 0
A63: =IFERROR(__xludf.DUMMYFUNCTION("""COMPUTED_VALUE"""),"Coding Pattern") -> Coding Pattern | B63: =IFERROR(__xludf.DUMMYFUNCTION("""COMPUTED_VALUE"""),"Coding Pattern") -> Coding Pattern | H63: 0 | I63: 0 | J63: 0
A64: =IFERROR(__xludf.DUMMYFUNCTION("""COMPUTED_VALUE"""),"Commit&PR rule") -> Commit&PR rule | B64: =IFERROR(__xludf.DUMMYFUNCTION("""COMPUTED_VALUE"""),"Commit&PR rule") -> Commit&PR rule | H64: 0 | I64: 0 | J64: 0
A65: =IFERROR(__xludf.DUMMYFUNCTION("""COMPUTED_VALUE"""),"Testing") -> Testing | B65: =IFERROR(__xludf.DUMMYFUNCTION("""COMPUTED_VALUE"""),"Testing") -> Testing | H65: 0 | I65: 0 | J65: 0
A66: =IFERROR(__xludf.DUMMYFUNCTION("""COMPUTED_VALUE"""),"Commit&PR rule") -> Commit&PR rule | B66: =IFERROR(__xludf.DUMMYFUNCTION("""COMPUTED_VALUE"""),"Commit&PR rule") -> Commit&PR rule | H66: 0 | I66: 0 | J66: 0
A67: =IFERROR(__xludf.DUMMYFUNCTION("""COMPUTED_VALUE"""),"Coding Pattern") -> Coding Pattern | B67: =IFERROR(__xludf.DUMMYFUNCTION("""COMPUTED_VALUE"""),"Coding Pattern") -> Coding Pattern | H67: 0 | I67: 0 | J67: 0
A68: =IFERROR(__xludf.DUMMYFUNCTION("""COMPUTED_VALUE"""),"Commit&PR rule") -> Commit&PR rule | B68: =IFERROR(__xludf.DUMMYFUNCTION("""COMPUTED_VALUE"""),"Commit&PR rule") -> Commit&PR rule | H68: 0 | I68: 0 | J68: 0
A69: =IFERROR(__xludf.DUMMYFUNCTION("""COMPUTED_VALUE"""),"Performance") -> Performance | B69: =IFERROR(__xludf.DUMMYFUNCTION("""COMPUTED_VALUE"""),"Performance") -> Performance | H69: 0 | I69: 0 | J69: 0
A70: =IFERROR(__xludf.DUMMYFUNCTION("""COMPUTED_VALUE"""),"Coding Pattern") -> Coding Pattern | B70: =IFERROR(__xludf.DUMMYFUNCTION("""COMPUTED_VALUE"""),"Coding Pattern") -> Coding Pattern | H70: 0 | I70: 0 | J70: 0
A71: =IFERROR(__xludf.DUMMYFUNCTION("""COMPUTED_VALUE"""),"Coding Pattern") -> Coding Pattern | B71: =IFERROR(__xludf.DUMMYFUNCTION("""COMPUTED_VALUE"""),"Coding Pattern") -> Coding Pattern | H71: 0 | I71: 0 | J71: 0
A72: =IFERROR(__xludf.DUMMYFUNCTION("""COMPUTED_VALUE"""),"Task Execution") -> Task Execution | B72: =IFERROR(__xludf.DUMMYFUNCTION("""COMPUTED_VALUE"""),"Task Execution") -> Task Execution | H72: 0 | I72: 0 | J72: 0
A73: =IFERROR(__xludf.DUMMYFUNCTION("""COMPUTED_VALUE"""),"Task Execution") -> Task Execution | B73: =IFERROR(__xludf.DUMMYFUNCTION("""COMPUTED_VALUE"""),"Task Execution") -> Task Execution | H73: 0 | I73: 0 | J73: 0
A74: =IFERROR(__xludf.DUMMYFUNCTION("""COMPUTED_VALUE"""),"Task Execution") -> Task Execution | B74: =IFERROR(__xludf.DUMMYFUNCTION("""COMPUTED_VALUE"""),"Task Execution") -> Task Execution | H74: 0 | I74: 0 | J74: 0
A75: =IFERROR(__xludf.DUMMYFUNCTION("""COMPUTED_VALUE"""),"Testing") -> Testing | B75: =IFERROR(__xludf.DUMMYFUNCTION("""COMPUTED_VALUE"""),"Build & Operation") -> Build & Operation | H75: 0 | I75: 0 | J75: 0
A76: =IFERROR(__xludf.DUMMYFUNCTION("""COMPUTED_VALUE"""),"Build & Operation") -> Build & Operation | B76: =IFERROR(__xludf.DUMMYFUNCTION("""COMPUTED_VALUE"""),"Testing") -> Testing | H76: 0 | I76: 0 | J76: 0
A77: =IFERROR(__xludf.DUMMYFUNCTION("""COMPUTED_VALUE"""),"Performance") -> Performance | B77: =IFERROR(__xludf.DUMMYFUNCTION("""COMPUTED_VALUE"""),"Performance") -> Performance | H77: 0 | I77: 0 | J77: 0
A78: =IFERROR(__xludf.DUMMYFUNCTION("""COMPUTED_VALUE"""),"Task Execution") -> Task Execution | B78: =IFERROR(__xludf.DUMMYFUNCTION("""COMPUTED_VALUE"""),"Task Execution") -> Task Execution | H78: 0 | I78: 0 | J78: 0
A79: =IFERROR(__xludf.DUMMYFUNCTION("""COMPUTED_VALUE"""),"Build & Operation") -> Build & Operation | B79: =IFERROR(__xludf.DUMMYFUNCTION("""COMPUTED_VALUE"""),"Task Execution") -> Task Execution | H79: 0 | I79: 0 | J79: 0
A80: =IFERROR(__xludf.DUMMYFUNCTION("""COMPUTED_VALUE"""),"Task Execution") -> Task Execution | B80: =IFERROR(__xludf.DUMMYFUNCTION("""COMPUTED_VALUE"""),"Task Execution") -> Task Execution | H80: 0 | I80: 0 | J80: 0
A81: =IFERROR(__xludf.DUMMYFUNCTION("""COMPUTED_VALUE"""),"Task Execution") -> Task Execution | B81: =IFERROR(__xludf.DUMMYFUNCTION("""COMPUTED_VALUE"""),"Task Execution") -> Task Execution | H81: 0 | I81: 0 | J81: 0
A82: =IFERROR(__xludf.DUMMYFUNCTION("""COMPUTED_VALUE"""),"Coding Pattern") -> Coding Pattern | B82: =IFERROR(__xludf.DUMMYFUNCTION("""COMPUTED_VALUE"""),"Coding Pattern") -> Coding Pattern | H82: 0 | I82: 0 | J82: 0
A83: =IFERROR(__xludf.DUMMYFUNCTION("""COMPUTED_VALUE"""),"Coding Pattern") -> Coding Pattern | B83: =IFERROR(__xludf.DUMMYFUNCTION("""COMPUTED_VALUE"""),"Coding Pattern") -> Coding Pattern | H83: 0 | I83: 0 | J83: 0
A84: =IFERROR(__xludf.DUMMYFUNCTION("""COMPUTED_VALUE"""),"Coding Pattern") -> Coding Pattern | B84: =IFERROR(__xludf.DUMMYFUNCTION("""COMPUTED_VALUE"""),"Coding Pattern") -> Coding Pattern | H84: 0 | I84: 0 | J84: 0
A85: =IFERROR(__xludf.DUMMYFUNCTION("""COMPUTED_VALUE"""),"Coding Pattern") -> Coding Pattern | B85: =IFERROR(__xludf.DUMMYFUNCTION("""COMPUTED_VALUE"""),"Coding Pattern") -> Coding Pattern | H85: 0 | I85: 0 | J85: 0
A86: =IFERROR(__xludf.DUMMYFUNCTION("""COMPUTED_VALUE"""),"Coding Pattern") -> Coding Pattern | B86: =IFERROR(__xludf.DUMMYFUNCTION("""COMPUTED_VALUE"""),"Coding Pattern") -> Coding Pattern | H86: 0 | I86: 0 | J86: 0
A87: =IFERROR(__xludf.DUMMYFUNCTION("""COMPUTED_VALUE"""),"Coding Pattern") -> Coding Pattern | B87: =IFERROR(__xludf.DUMMYFUNCTION("""COMPUTED_VALUE"""),"Coding Pattern") -> Coding Pattern | H87: 0 | I87: 0 | J87: 0
A88: =IFERROR(__xludf.DUMMYFUNCTION("""COMPUTED_VALUE"""),"Build & Operation") -> Build & Operation | B88: =IFERROR(__xludf.DUMMYFUNCTION("""COMPUTED_VALUE"""),"Build & Operation") -> Build & Operation | H88: 0 | I88: 0 | J88: 0
A89: =IFERROR(__xludf.DUMMYFUNCTION("""COMPUTED_VALUE"""),"Coding Style") -> Coding Style | B89: =IFERROR(__xludf.DUMMYFUNCTION("""COMPUTED_VALUE"""),"Coding Style") -> Coding Style | H89: 0 | I89: 0 | J89: 0
A90: =IFERROR(__xludf.DUMMYFUNCTION("""COMPUTED_VALUE"""),"Testing") -> Testing | B90: =IFERROR(__xludf.DUMMYFUNCTION("""COMPUTED_VALUE"""),"Testing") -> Testing | H90: 0 | I90: 0 | J90: 0
A91: =IFERROR(__xludf.DUMMYFUNCTION("""COMPUTED_VALUE"""),"Coding Style") -> Coding Style | B91: =IFERROR(__xludf.DUMMYFUNCTION("""COMPUTED_VALUE"""),"Coding Style") -> Coding Style | H91: 0 | I91: 0 | J91: 0
A92: =IFERROR(__xludf.DUMMYFUNCTION("""COMPUTED_VALUE"""),"Testing") -> Testing | B92: =IFERROR(__xludf.DUMMYFUNCTION("""COMPUTED_VALUE"""),"Testing") -> Testing | H92: 0 | I92: 0 | J92: 0
A93: =IFERROR(__xludf.DUMMYFUNCTION("""COMPUTED_VALUE"""),"Build & Operation") -> Build & Operation | B93: =IFERROR(__xludf.DUMMYFUNCTION("""COMPUTED_VALUE"""),"Build & Operation") -> Build & Operation | H93: 0 | I93: 0 | J93: 0
A94: =IFERROR(__xludf.DUMMYFUNCTION("""COMPUTED_VALUE"""),"Testing") -> Testing | B94: =IFERROR(__xludf.DUMMYFUNCTION("""COMPUTED_VALUE"""),"Testing") -> Testing | H94: 0 | I94: 0 | J94: 0
A95: =IFERROR(__xludf.DUMMYFUNCTION("""COMPUTED_VALUE"""),"Testing") -> Testing | B95: =IFERROR(__xludf.DUMMYFUNCTION("""COMPUTED_VALUE"""),"Testing") -> Testing | H95: 0 | I95: 0 | J95: 0
A96: =IFERROR(__xludf.DUMMYFUNCTION("""COMPUTED_VALUE"""),"Coding Pattern") -> Coding Pattern | B96: =IFERROR(__xludf.DUMMYFUNCTION("""COMPUTED_VALUE"""),"Coding Pattern") -> Coding Pattern | H96: 0 | I96: 0 | J96: 0
A97: =IFERROR(__xludf.DUMMYFUNCTION("""COMPUTED_VALUE"""),"Coding Pattern") -> Coding Pattern | B97: =IFERROR(__xludf.DUMMYFUNCTION("""COMPUTED_VALUE"""),"Coding Pattern") -> Coding Pattern | H97: 0 | I97: 0 | J97: 0
A98: =IFERROR(__xludf.DUMMYFUNCTION("""COMPUTED_VALUE"""),"Task Execution") -> Task Execution | B98: =IFERROR(__xludf.DUMMYFUNCTION("""COMPUTED_VALUE"""),"Task Execution") -> Task Execution | H98: 0 | I98: 0 | J98: 0
A99: =IFERROR(__xludf.DUMMYFUNCTION("""COMPUTED_VALUE"""),"Task Execution") -> Task Execution | B99: =IFERROR(__xludf.DUMMYFUNCTION("""COMPUTED_VALUE"""),"Task Execution") -> Task Execution | H99: 0 | I99: 0 | J99: 0
A100: =IFERROR(__xludf.DUMMYFUNCTION("""COMPUTED_VALUE"""),"Coding Pattern") -> Coding Pattern | B100: =IFERROR(__xludf.DUMMYFUNCTION("""COMPUTED_VALUE"""),"Coding Pattern") -> Coding Pattern | H100: 0 | I100: 0 | J100: 0
...
